Workbook

Sheet Сводка
A1: The Aldera · финансовая модель · сводка
A2: 518 GROUP LLC. 4 продукта Vox Nutrition, каналы TikTok Shop, Shopify, Amazon. Старт продаж 20.11.2026. Вложение двумя траншами. Платная реклама только Spark Ads на выстрелившие ролики, с февраля 2027.
A3: Активный сценарий (1 конс., 2 база, 3 опт.): | C3: =Допущения!B3 -> 2
A5: Показатель | B5: Год 1 | C5: Год 2 | D5: Год 3
A6: Выручка | B6: ='Итоги по годам'!B16 -> 3677785.5 | C6: ='Итоги по годам'!C16 -> 12077196 | D6: ='Итоги по годам'!D16 -> 21146706
A7: Маржинальная прибыль | B7: ='Итоги по годам'!B27 -> 1388534.1 | C7: ='Итоги по годам'!C27 -> 5197233.3 | D7: ='Итоги по годам'!D27 -> 9558712.3
A8: Маржинальность | B8: ='Итоги по годам'!B41 -> 0.37754625 | C8: ='Итоги по годам'!C41 -> 0.43033443 | D8: ='Итоги по годам'!D41 -> 0.45201898
A9: Постоянные расходы | B9: ='Итоги по годам'!B34 -> 200450.8 | C9: ='Итоги по годам'!C34 -> 596585.6 | D9: ='Итоги по годам'!D34 -> 829532.35
A10: EBITDA | B10: ='Итоги по годам'!B35 -> 1188083.3 | C10: ='Итоги по годам'!C35 -> 4600647.7 | D10: ='Итоги по годам'!D35 -> 8729180
A11: Рентабельность по EBITDA | B11: ='Итоги по годам'!B42 -> 0.32304313 | C11: ='Итоги по годам'!C42 -> 0.38093674 | D11: ='Итоги по годам'!D42 -> 0.41279148
A12: Чистая прибыль после налога (оценка) | B12: ='Итоги по годам'!B37 -> 891062.49 | C12: ='Итоги по годам'!C37 -> 3450485.8 | D12: ='Итоги по годам'!D37 -> 6546885
A13: Заказов всего | B13: ='Итоги по годам'!B9 -> 74271.075 | C13: ='Итоги по годам'!C9 -> 237924.82 | D13: ='Итоги по годам'!D9 -> 405293.53
A14: Подписчиков на конец года | B14: ='Итоги по годам'!B43 -> 3893.9825 | C14: ='Итоги по годам'!C43 -> 10187.6 | D14: ='Итоги по годам'!D43 -> 17004.955
A15: Криейторов на конец года | B15: ='Итоги по годам'!B44 -> 150 | C15: ='Итоги по годам'!C44 -> 294 | D15: ='Итоги по годам'!D44 -> 400
A16: Деньги на счёте на конец года | B16: ='Итоги по годам'!B45 -> 624408.93 | C16: ='Итоги по годам'!C45 -> 3804061.4 | D16: ='Итоги по годам'!D45 -> 10138854
A18: Минимум денег на счёте | B18: ='Итоги по годам'!E46 -> -8323.2387
A19: Месяц выхода на темп $1 млн EBITDA в год (1 = ноябрь 2026) | B19: ='Итоги по годам'!E47 -> 7
A21: Главные выводы (базовый сценарий, снимок 03.10.2026)
A22: • Вложения окупаются EBITDA на 2-м месяце (декабрь 2026), темп $1 млн EBITDA в год на 7-м месяце (май 2027).
A23: • Узкое место декабрь 2026: при запасе товара 1,3 месяца денег не хватает на $8 323. Решение: второй транш $21 000 вместо $5 000 (покрывает 90% исходов Монте-Карло) или запас 1,0 месяца в декабре.
A24: • Монте-Карло, 5 000 прогонов: EBITDA года 1 от $547 тыс. (P10) до $1 391 тыс. (P90), медиана $875 тыс.
A25: • Вероятность EBITDA года 2 не меньше $1 млн: больше 99%. Вероятность, что при транше $5 000 денег не хватит: 68%, нехватка до $15 508 (P90).
A26: • Главные рычаги прибыли: конверсия просмотра в заказ, просмотры на ролик, скорость набора криейторов, переход в подписку.
A27: • Без Amazon EBITDA года 1 остаётся в плюсе уже при конверсии 0,0041%; $1 млн EBITDA во 2-м году без Amazon при конверсии от 0,016%.

Sheet Итоги по годам
A1: The Aldera · итоги по годам модели
A2: Год 1: ноябрь 2026 - октябрь 2027. Год 2: ноябрь 2027 - октябрь 2028. Год 3: ноябрь 2028 - октябрь 2029. Сценарий на листе «Допущения», ячейка B3.
A4: Показатель | B4: Год 1 | C4: Год 2 | D4: Год 3 | E4: Итого 3 года
A5: Заказы TikTok | B5: =SUMIF(Модель!$D$5:$AM$5,1,Модель!$D$12:$AM$12) -> 34358 | C5: =SUMIF(Модель!$D$5:$AM$5,2,Модель!$D$12:$AM$12) -> 87516 | D5: =SUMIF(Модель!$D$5:$AM$5,3,Модель!$D$12:$AM$12) -> 140730.72 | E5: =SUM(B5:D5) -> 262604.72
A6: Заказы Shopify прямые | B6: =SUMIF(Модель!$D$5:$AM$5,1,Модель!$D$13:$AM$13) -> 3435.8 | C6: =SUMIF(Модель!$D$5:$AM$5,2,Модель!$D$13:$AM$13) -> 8751.6 | D6: =SUMIF(Модель!$D$5:$AM$5,3,Модель!$D$13:$AM$13) -> 14073.072 | E6: =SUM(B6:D6) -> 26260.472
A7: Заказы подписки | B7: =SUMIF(Модель!$D$5:$AM$5,1,Модель!$D$16:$AM$16) -> 17750.875 | C7: =SUMIF(Модель!$D$5:$AM$5,2,Модель!$D$16:$AM$16) -> 81465.221 | D7: =SUMIF(Модель!$D$5:$AM$5,3,Модель!$D$16:$AM$16) -> 164032.14 | E7: =SUM(B7:D7) -> 263248.24
A8: Заказы Amazon | B8: =SUMIF(Модель!$D$5:$AM$5,1,Модель!$D$18:$AM$18) -> 18726.4 | C8: =SUMIF(Модель!$D$5:$AM$5,2,Модель!$D$18:$AM$18) -> 60192 | D8: =SUMIF(Модель!$D$5:$AM$5,3,Модель!$D$18:$AM$18) -> 86457.6 | E8: =SUM(B8:D8) -> 165376
A9: Всего заказов | B9: =SUMIF(Модель!$D$5:$AM$5,1,Модель!$D$19:$AM$19) -> 74271.075 | C9: =SUMIF(Модель!$D$5:$AM$5,2,Модель!$D$19:$AM$19) -> 237924.82 | D9: =SUMIF(Модель!$D$5:$AM$5,3,Модель!$D$19:$AM$19) -> 405293.53 | E9: =SUM(B9:D9) -> 717489.43
A10: Банок продано | B10: =SUMIF(Модель!$D$5:$AM$5,1,Модель!$D$25:$AM$25) -> 118692.18 | C10: =SUMIF(Модель!$D$5:$AM$5,2,Модель!$D$25:$AM$25) -> 395480.28 | D10: =SUMIF(Модель!$D$5:$AM$5,3,Модель!$D$25:$AM$25) -> 699115.18 | E10: =SUM(B10:D10) -> 1213287.6
A12: Выручка TikTok Shop | B12: =SUMIF(Модель!$D$5:$AM$5,1,Модель!$D$32:$AM$32) -> 1745386.4 | C12: =SUMIF(Модель!$D$5:$AM$5,2,Модель!$D$32:$AM$32) -> 4445812.8 | D12: =SUMIF(Модель!$D$5:$AM$5,3,Модель!$D$32:$AM$32) -> 7149120.6 | E12: =SUM(B12:D12) -> 13340320
A13: Выручка Shopify: первые | B13: =SUMIF(Модель!$D$5:$AM$5,1,Модель!$D$33:$AM$33) -> 174538.64 | C13: =SUMIF(Модель!$D$5:$AM$5,2,Модель!$D$33:$AM$33) -> 444581.28 | D13: =SUMIF(Модель!$D$5:$AM$5,3,Модель!$D$33:$AM$33) -> 714912.06 | E13: =SUM(B13:D13) -> 1334032
A14: Выручка Shopify: подписка | B14: =SUMIF(Модель!$D$5:$AM$5,1,Модель!$D$34:$AM$34) -> 1117417.5 | C14: =SUMIF(Модель!$D$5:$AM$5,2,Модель!$D$34:$AM$34) -> 5128235.7 | D14: =SUMIF(Модель!$D$5:$AM$5,3,Модель!$D$34:$AM$34) -> 10325823 | E14: =SUM(B14:D14) -> 16571476
A15: Выручка Amazon | B15: =SUMIF(Модель!$D$5:$AM$5,1,Модель!$D$35:$AM$35) -> 640442.88 | C15: =SUMIF(Модель!$D$5:$AM$5,2,Модель!$D$35:$AM$35) -> 2058566.4 | D15: =SUMIF(Модель!$D$5:$AM$5,3,Модель!$D$35:$AM$35) -> 2956849.9 | E15: =SUM(B15:D15) -> 5655859.2
A16: Выручка всего | B16: =SUMIF(Модель!$D$5:$AM$5,1,Модель!$D$36:$AM$36) -> 3677785.5 | C16: =SUMIF(Модель!$D$5:$AM$5,2,Модель!$D$36:$AM$36) -> 12077196 | D16: =SUMIF(Модель!$D$5:$AM$5,3,Модель!$D$36:$AM$36) -> 21146706 | E16: =SUM(B16:D16) -> 36901687
A18: Товар (Vox) | B18: =SUMIF(Модель!$D$5:$AM$5,1,Модель!$D$38:$AM$38) -> 766640.74 | C18: =SUMIF(Модель!$D$5:$AM$5,2,Модель!$D$38:$AM$38) -> 2373776.3 | D18: =SUMIF(Модель!$D$5:$AM$5,3,Модель!$D$38:$AM$38) -> 4124801.4 | E18: =SUM(B18:D18) -> 7265218.4
A19: Комиссия TikTok Shop | B19: =SUMIF(Модель!$D$5:$AM$5,1,Модель!$D$39:$AM$39) -> 139630.91 | C19: =SUMIF(Модель!$D$5:$AM$5,2,Модель!$D$39:$AM$39) -> 355665.02 | D19: =SUMIF(Модель!$D$5:$AM$5,3,Модель!$D$39:$AM$39) -> 571929.65 | E19: =SUM(B19:D19) -> 1067225.6
A20: Комиссия криейторов | B20: =SUMIF(Модель!$D$5:$AM$5,1,Модель!$D$40:$AM$40) -> 523615.92 | C20: =SUMIF(Модель!$D$5:$AM$5,2,Модель!$D$40:$AM$40) -> 1333743.8 | D20: =SUMIF(Модель!$D$5:$AM$5,3,Модель!$D$40:$AM$40) -> 2144736.2 | E20: =SUM(B20:D20) -> 4002095.9
A21: Эквайринг Shopify | B21: =SUMIF(Модель!$D$5:$AM$5,1,Модель!$D$41:$AM$41) -> 43822.732 | C21: =SUMIF(Модель!$D$5:$AM$5,2,Модель!$D$41:$AM$41) -> 188676.74 | D21: =SUMIF(Модель!$D$5:$AM$5,3,Модель!$D$41:$AM$41) -> 373612.89 | E21: =SUM(B21:D21) -> 606112.36
A22: Amazon: комиссия и FBA | B22: =SUMIF(Модель!$D$5:$AM$5,1,Модель!$D$42:$AM$42) -> 210110.21 | C22: =SUMIF(Модель!$D$5:$AM$5,2,Модель!$D$42:$AM$42) -> 675354.24 | D22: =SUMIF(Модель!$D$5:$AM$5,3,Модель!$D$42:$AM$42) -> 970054.27 | E22: =SUM(B22:D22) -> 1855518.7
A23: Amazon: реклама PPC | B23: =SUMIF(Модель!$D$5:$AM$5,1,Модель!$D$43:$AM$43) -> 96066.432 | C23: =SUMIF(Модель!$D$5:$AM$5,2,Модель!$D$43:$AM$43) -> 308784.96 | D23: =SUMIF(Модель!$D$5:$AM$5,3,Модель!$D$43:$AM$43) -> 443527.49 | E23: =SUM(B23:D23) -> 848378.88
A24: Доставка покупателю | B24: =SUMIF(Модель!$D$5:$AM$5,1,Модель!$D$44:$AM$44) -> 292302.01 | C24: =SUMIF(Модель!$D$5:$AM$5,2,Модель!$D$44:$AM$44) -> 954798.96 | D24: =SUMIF(Модель!$D$5:$AM$5,3,Модель!$D$44:$AM$44) -> 1726953.4 | E24: =SUM(B24:D24) -> 2974054.4
A25: Склад-отправщик | B25: =SUMIF(Модель!$D$5:$AM$5,1,Модель!$D$45:$AM$45) -> 138861.69 | C25: =SUMIF(Модель!$D$5:$AM$5,2,Модель!$D$45:$AM$45) -> 444332.05 | D25: =SUMIF(Модель!$D$5:$AM$5,3,Модель!$D$45:$AM$45) -> 797089.83 | E25: =SUM(B25:D25) -> 1380283.6
A26: Возвраты | B26: =SUMIF(Модель!$D$5:$AM$5,1,Модель!$D$46:$AM$46) -> 78200.716 | C26: =SUMIF(Модель!$D$5:$AM$5,2,Модель!$D$46:$AM$46) -> 244830.72 | D26: =SUMIF(Модель!$D$5:$AM$5,3,Модель!$D$46:$AM$46) -> 435288.32 | E26: =SUM(B26:D26) -> 758319.76
A27: Маржинальная прибыль | B27: =SUMIF(Модель!$D$5:$AM$5,1,Модель!$D$48:$AM$48) -> 1388534.1 | C27: =SUMIF(Модель!$D$5:$AM$5,2,Модель!$D$48:$AM$48) -> 5197233.3 | D27: =SUMIF(Модель!$D$5:$AM$5,3,Модель!$D$48:$AM$48) -> 9558712.3 | E27: =SUM(B27:D27) -> 16144480
A29: Сервисы и ПО | B29: =SUMIF(Модель!$D$5:$AM$5,1,Модель!$D$51:$AM$51) -> 6000 | C29: =SUMIF(Модель!$D$5:$AM$5,2,Модель!$D$51:$AM$51) -> 12000 | D29: =SUMIF(Модель!$D$5:$AM$5,3,Модель!$D$51:$AM$51) -> 18000 | E29: =SUM(B29:D29) -> 36000
A30: Страховка | B30: =SUMIF(Модель!$D$5:$AM$5,1,Модель!$D$52:$AM$52) -> 2150 | C30: =SUMIF(Модель!$D$5:$AM$5,2,Модель!$D$52:$AM$52) -> 6000 | D30: =SUMIF(Модель!$D$5:$AM$5,3,Модель!$D$52:$AM$52) -> 6000 | E30: =SUM(B30:D30) -> 14150
A31: Бухгалтерия и юристы | B31: =SUMIF(Модель!$D$5:$AM$5,1,Модель!$D$53:$AM$53) -> 3600 | C31: =SUMIF(Модель!$D$5:$AM$5,2,Модель!$D$53:$AM$53) -> 3600 | D31: =SUMIF(Модель!$D$5:$AM$5,3,Модель!$D$53:$AM$53) -> 3600 | E31: =SUM(B31:D31) -> 10800
A32: Команда | B32: =SUMIF(Модель!$D$5:$AM$5,1,Модель!$D$54:$AM$54) -> 68000 | C32: =SUMIF(Модель!$D$5:$AM$5,2,Модель!$D$54:$AM$54) -> 233000 | D32: =SUMIF(Модель!$D$5:$AM$5,3,Модель!$D$54:$AM$54) -> 252000 | E32: =SUM(B32:D32) -> 553000
A33: Реклама: Spark Ads и прочая | B33: =SUMIF(Модель!$D$5:$AM$5,1,Модель!$D$55:$AM$55) -> 120700.8 | C33: =SUMIF(Модель!$D$5:$AM$5,2,Модель!$D$55:$AM$55) -> 341985.6 | D33: =SUMIF(Модель!$D$5:$AM$5,3,Модель!$D$55:$AM$55) -> 549932.35 | E33: =SUM(B33:D33) -> 1012618.8
A34: Постоянные расходы | B34: =SUMIF(Модель!$D$5:$AM$5,1,Модель!$D$56:$AM$56) -> 200450.8 | C34: =SUMIF(Модель!$D$5:$AM$5,2,Модель!$D$56:$AM$56) -> 596585.6 | D34: =SUMIF(Модель!$D$5:$AM$5,3,Модель!$D$56:$AM$56) -> 829532.35 | E34: =SUM(B34:D34) -> 1626568.8
A35: EBITDA (прибыль до налога) | B35: =SUMIF(Модель!$D$5:$AM$5,1,Модель!$D$57:$AM$57) -> 1188083.3 | C35: =SUMIF(Модель!$D$5:$AM$5,2,Модель!$D$57:$AM$57) -> 4600647.7 | D35: =SUMIF(Модель!$D$5:$AM$5,3,Модель!$D$57:$AM$57) -> 8729180 | E35: =SUM(B35:D35) -> 14517911
A36: Налог, оценка | B36: =SUMIF(Модель!$D$5:$AM$5,1,Модель!$D$58:$AM$58) -> 297020.83 | C36: =SUMIF(Модель!$D$5:$AM$5,2,Модель!$D$58:$AM$58) -> 1150161.9 | D36: =SUMIF(Модель!$D$5:$AM$5,3,Модель!$D$58:$AM$58) -> 2182295 | E36: =SUM(B36:D36) -> 3629477.8
A37: Чистая прибыль | B37: =SUMIF(Модель!$D$5:$AM$5,1,Модель!$D$59:$AM$59) -> 891062.49 | C37: =SUMIF(Модель!$D$5:$AM$5,2,Модель!$D$59:$AM$59) -> 3450485.8 | D37: =SUMIF(Модель!$D$5:$AM$5,3,Модель!$D$59:$AM$59) -> 6546885 | E37: =SUM(B37:D37) -> 10888433
A39: Закупка товара у Vox | B39: =SUMIF(Модель!$D$5:$AM$5,1,Модель!$D$69:$AM$69) -> 934218.5 | C39: =SUMIF(Модель!$D$5:$AM$5,2,Модель!$D$69:$AM$69) -> 2557745.5 | D39: =SUMIF(Модель!$D$5:$AM$5,3,Модель!$D$69:$AM$69) -> 4267797 | E39: =SUM(B39:D39) -> 7759761
A41: Маржинальность | B41: =IF(B16=0,0,B27/B16) -> 0.37754625 | C41: =IF(C16=0,0,C27/C16) -> 0.43033443 | D41: =IF(D16=0,0,D27/D16) -> 0.45201898 | E41: =IF(E16=0,0,E27/E16) -> 0.43749977
A42: Рентабельность по EBITDA | B42: =IF(B16=0,0,B35/B16) -> 0.32304313 | C42: =IF(C16=0,0,C35/C16) -> 0.38093674 | D42: =IF(D16=0,0,D35/D16) -> 0.41279148 | E42: =IF(E16=0,0,E35/E16) -> 0.39342133
A43: Подписчиков на конец года | B43: =INDEX(Модель!$D$15:$AM$15,12) -> 3893.9825 | C43: =INDEX(Модель!$D$15:$AM$15,24) -> 10187.6 | D43: =INDEX(Модель!$D$15:$AM$15,36) -> 17004.955
A44: Криейторов на конец года | B44: =INDEX(Модель!$D$9:$AM$9,12) -> 150 | C44: =INDEX(Модель!$D$9:$AM$9,24) -> 294 | D44: =INDEX(Модель!$D$9:$AM$9,36) -> 400
A45: Деньги на счёте на конец года | B45: =INDEX(Модель!$D$73:$AM$73,12) -> 624408.93 | C45: =INDEX(Модель!$D$73:$AM$73,24) -> 3804061.4 | D45: =INDEX(Модель!$D$73:$AM$73,36) -> 10138854
A46: Минимум денег на счёте за 3 года | E46: =MIN(Модель!$C$73:$AM$73) -> -8323.2387
A47: Месяц выхода на темп $1 млн EBITDA в год | E47: =IFERROR(MATCH(TRUE(),INDEX(Модель!$D$57:$AM$57*12>=1000000,0),0),"нет") -> 7
A48: Окупаемость вложений, месяц (накопленная EBITDA > вложений) | E48: см. лист «Сводка»

Sheet KPI по кварталам
A1: KPI по кварталам: цели для ежемесячного контроля
A2: Квартал 1 = ноябрь 2026 - январь 2027. Живые формулы из листа «Модель».
A4: Показатель | B4: Q1 ноя26-янв27 | C4: Q2 фев-апр27 | D4: Q3 май-июл27 | E4: Q4 авг-окт27 | F4: Q5 ноя27-янв28 | G4: Q6 фев-апр28 | H4: Q7 май-июл28 | I4: Q8 авг-окт28 | J4: Q9 | K4: Q10 | L4: Q11 | M4: Q12
A5: Криейторов на конец квартала | B5: =Модель!F9 -> 60 | C5: =Модель!I9 -> 90 | D5: =Модель!L9 -> 120 | E5: =Модель!O9 -> 150 | F5: =Модель!R9 -> 186 | G5: =Модель!U9 -> 222 | H5: =Модель!X9 -> 258 | I5: =Модель!AA9 -> 294 | J5: =Модель!AD9 -> 330 | K5: =Модель!AG9 -> 366 | L5: =Модель!AJ9 -> 400 | M5: =Модель!AM9 -> 400
A6: Роликов вышло | B6: =SUM(Модель!D10:F10) -> 1026.6667 | C6: =SUM(Модель!G10:I10) -> 1920 | D6: =SUM(Модель!J10:L10) -> 2640 | E6: =SUM(Модель!M10:O10) -> 3360 | F6: =SUM(Модель!P10:R10) -> 4176 | G6: =SUM(Модель!S10:U10) -> 5040 | H6: =SUM(Модель!V10:X10) -> 5904 | I6: =SUM(Модель!Y10:AA10) -> 6768 | J6: =SUM(Модель!AB10:AD10) -> 7632 | K6: =SUM(Модель!AE10:AG10) -> 8496 | L6: =SUM(Модель!AH10:AJ10) -> 9344 | M6: =SUM(Модель!AK10:AM10) -> 9600
A7: Просмотров, млн | B7: =SUM(Модель!D11:F11)/1000000 -> 5.1333333 | C7: =SUM(Модель!G11:I11)/1000000 -> 9.6 | D7: =SUM(Модель!J11:L11)/1000000 -> 13.2 | E7: =SUM(Модель!M11:O11)/1000000 -> 16.8 | F7: =SUM(Модель!P11:R11)/1000000 -> 20.88 | G7: =SUM(Модель!S11:U11)/1000000 -> 25.2 | H7: =SUM(Модель!V11:X11)/1000000 -> 29.52 | I7: =SUM(Модель!Y11:AA11)/1000000 -> 33.84 | J7: =SUM(Модель!AB11:AD11)/1000000 -> 38.16 | K7: =SUM(Модель!AE11:AG11)/1000000 -> 42.48 | L7: =SUM(Модель!AH11:AJ11)/1000000 -> 46.72 | M7: =SUM(Модель!AK11:AM11)/1000000 -> 48
A8: Заказы TikTok | B8: =SUM(Модель!D12:F12) -> 3470 | C8: =SUM(Модель!G12:I12) -> 7488 | D8: =SUM(Модель!J12:L12) -> 10296 | E8: =SUM(Модель!M12:O12) -> 13104 | F8: =SUM(Модель!P12:R12) -> 18439.2 | G8: =SUM(Модель!S12:U12) -> 19656 | H8: =SUM(Модель!V12:X12) -> 23025.6 | I8: =SUM(Модель!Y12:AA12) -> 26395.2 | J8: =SUM(Модель!AB12:AD12) -> 33714.72 | K8: =SUM(Модель!AE12:AG12) -> 33134.4 | L8: =SUM(Модель!AH12:AJ12) -> 36441.6 | M8: =SUM(Модель!AK12:AM12) -> 37440
A9: Заказы Shopify первые | B9: =SUM(Модель!D13:F13) -> 347 | C9: =SUM(Модель!G13:I13) -> 748.8 | D9: =SUM(Модель!J13:L13) -> 1029.6 | E9: =SUM(Модель!M13:O13) -> 1310.4 | F9: =SUM(Модель!P13:R13) -> 1843.92 | G9: =SUM(Модель!S13:U13) -> 1965.6 | H9: =SUM(Модель!V13:X13) -> 2302.56 | I9: =SUM(Модель!Y13:AA13) -> 2639.52 | J9: =SUM(Модель!AB13:AD13) -> 3371.472 | K9: =SUM(Модель!AE13:AG13) -> 3313.44 | L9: =SUM(Модель!AH13:AJ13) -> 3644.16 | M9: =SUM(Модель!AK13:AM13) -> 3744
A10: Заказы подписки | B10: =SUM(Модель!D16:F16) -> 386.331 | C10: =SUM(Модель!G16:I16) -> 2543.4388 | D10: =SUM(Модель!J16:L16) -> 5650.3021 | E10: =SUM(Модель!M16:O16) -> 9170.8026 | F10: =SUM(Модель!P16:R16) -> 13405.045 | G10: =SUM(Модель!S16:U16) -> 18182.771 | H10: =SUM(Модель!V16:X16) -> 22581.872 | I10: =SUM(Модель!Y16:AA16) -> 27295.533 | J10: =SUM(Модель!AB16:AD16) -> 32933.025 | K10: =SUM(Модель!AE16:AG16) -> 38926.647 | L10: =SUM(Модель!AH16:AJ16) -> 43731.024 | M10: =SUM(Модель!AK16:AM16) -> 48441.444
A11: Подписчиков на конец | B11: =Модель!F15 -> 533.9169 | C11: =Модель!I15 -> 1515.093 | D11: =Модель!L15 -> 2648.9028 | E11: =Модель!O15 -> 3893.9825 | F11: =Модель!R15 -> 5595.946 | G11: =Модель!U15 -> 7020.9089 | H11: =Модель!X15 -> 8561.9457 | I11: =Модель!AA15 -> 10187.6 | J11: =Модель!AD15 -> 12457.227 | K11: =Модель!AG15 -> 14031.738 | L11: =Модель!AJ15 -> 15671.5 | M11: =Модель!AM15 -> 17004.955
A12: Заказы Amazon | B12: =SUM(Модель!D18:F18) -> 0 | C12: =SUM(Модель!G18:I18) -> 1722.6667 | D12: =SUM(Модель!J18:L18) -> 6384 | E12: =SUM(Модель!M18:O18) -> 10619.733 | F12: =SUM(Модель!P18:R18) -> 12585.6 | G12: =SUM(Модель!S18:U18) -> 14227.2 | H12: =SUM(Модель!V18:X18) -> 15868.8 | I12: =SUM(Модель!Y18:AA18) -> 17510.4 | J12: =SUM(Модель!AB18:AD18) -> 19152 | K12: =SUM(Модель!AE18:AG18) -> 20793.6 | L12: =SUM(Модель!AH18:AJ18) -> 22435.2 | M12: =SUM(Модель!AK18:AM18) -> 24076.8
A13: Выручка | B13: =SUM(Модель!D36:F36) -> 218223.14 | C13: =SUM(Модель!G36:I36) -> 637454.11 | D13: =SUM(Модель!J36:L36) -> 1149359.8 | E13: =SUM(Модель!M36:O36) -> 1672748.4 | F13: =SUM(Модель!P36:R36) -> 2304657.6 | G13: =SUM(Модель!S36:U36) -> 2729553 | H13: =SUM(Модель!V36:X36) -> 3250912.3 | I13: =SUM(Модель!Y36:AA36) -> 3792073.3 | J13: =SUM(Модель!AB36:AD36) -> 4612110.9 | K13: =SUM(Модель!AE36:AG36) -> 5013123.8 | L13: =SUM(Модель!AH36:AJ36) -> 5556508.4 | M13: =SUM(Модель!AK36:AM36) -> 5964962.7
A14: Маржинальная прибыль | B14: =SUM(Модель!D48:F48) -> 63785.236 | C14: =SUM(Модель!G48:I48) -> 223114.41 | D14: =SUM(Модель!J48:L48) -> 434922.5 | E14: =SUM(Модель!M48:O48) -> 666711.97 | F14: =SUM(Модель!P48:R48) -> 941963.37 | G14: =SUM(Модель!S48:U48) -> 1169520.9 | H14: =SUM(Модель!V48:X48) -> 1416428.1 | I14: =SUM(Модель!Y48:AA48) -> 1669321 | J14: =SUM(Модель!AB48:AD48) -> 2025862.9 | K14: =SUM(Модель!AE48:AG48) -> 2264742.9 | L14: =SUM(Модель!AH48:AJ48) -> 2525473.5 | M14: =SUM(Модель!AK48:AM48) -> 2742633
A15: EBITDA | B15: =SUM(Модель!D57:F57) -> 60935.236 | C15: =SUM(Модель!G57:I57) -> 180003.61 | D15: =SUM(Модель!J57:L57) -> 370838.9 | E15: =SUM(Модель!M57:O57) -> 576305.57 | F15: =SUM(Модель!P57:R57) -> 816508.65 | G15: =SUM(Модель!S57:U57) -> 1028311.3 | H15: =SUM(Модель!V57:X57) -> 1258051.2 | I15: =SUM(Модель!Y57:AA57) -> 1497776.6 | J15: =SUM(Модель!AB57:AD57) -> 1824216.1 | K15: =SUM(Модель!AE57:AG57) -> 2065363.9 | L15: =SUM(Модель!AH57:AJ57) -> 2313171 | M15: =SUM(Модель!AK57:AM57) -> 2526429
A16: Закупка у Vox | B16: =SUM(Модель!D69:F69) -> 75472.5 | C16: =SUM(Модель!G69:I69) -> 182142.5 | D16: =SUM(Модель!J69:L69) -> 286350.5 | E16: =SUM(Модель!M69:O69) -> 390253 | F16: =SUM(Модель!P69:R69) -> 493635.5 | G16: =SUM(Модель!S69:U69) -> 577216 | H16: =SUM(Модель!V69:X69) -> 680785 | I16: =SUM(Модель!Y69:AA69) -> 806109 | J16: =SUM(Модель!AB69:AD69) -> 936990 | K16: =SUM(Модель!AE69:AG69) -> 1025493 | L16: =SUM(Модель!AH69:AJ69) -> 1124077 | M16: =SUM(Модель!AK69:AM69) -> 1181237
A17: Деньги на конец квартала | B17: =Модель!F73 -> -246.78277 | C17: =Модель!I73 -> 60870.341 | D17: =Модель!L73 -> 266721.67 | E17: =Модель!O73 -> 624408.93 | F17: =Модель!R73 -> 1171509 | G17: =Модель!U73 -> 1890211.2 | H17: =Модель!X73 -> 2766204.8 | I17: =Модель!AA73 -> 3804061.4 | J17: =Модель!AD73 -> 5096261.9 | K17: =Модель!AG73 -> 6593982.1 | L17: =Модель!AJ73 -> 8267030.4 | M17: =Модель!AM73 -> 10138854

Sheet Юнит-экономика
A1: Юнит-экономика: прибыль с банки и с заказа по каналам
A3: Продукт | B3: Розница | C3: Банка @1 000 | D3: Банка @5 000 | E3: Прибыль TikTok | F3: Маржа TikTok | G3: Прибыль Shopify | H3: Маржа Shopify | I3: Прибыль Amazon | J3: Маржа Amazon
A4: Colostrum | B4: =Допущения!$C$59 -> 39.95 | C4: =Допущения!$K$59*Допущения!$E$19 -> 7.97 | D4: =Допущения!$M$59*Допущения!$E$19 -> 7.67 | E4: =B4-C4-B4*(Допущения!$B$26+Допущения!$B$29+Допущения!$B$30)-Допущения!$D$59-Допущения!$B$39 -> 8.6005 | F4: =E4/B4 -> 0.2152816 | G4: =B4-C4-B4*(Допущения!$B$31+Допущения!$B$33)-Допущения!$B$32-Допущения!$D$59-Допущения!$B$39 -> 22.72245 | H4: =G4/B4 -> 0.56877222 | I4: =B4-C4-B4*(Допущения!$B$34+Допущения!$E$17)-Допущения!$E$59 -> 13.445 | J4: =I4/B4 -> 0.33654568
A5: Women's Probiotic | B5: =Допущения!$C$60 -> 34.95 | C5: =Допущения!$K$60*Допущения!$E$19 -> 7.44 | D5: =Допущения!$M$60*Допущения!$E$19 -> 6.94 | E5: =B5-C5-B5*(Допущения!$B$26+Допущения!$B$29+Допущения!$B$30)-Допущения!$D$60-Допущения!$B$39 -> 7.1805 | F5: =E5/B5 -> 0.20545064 | G5: =B5-C5-B5*(Допущения!$B$31+Допущения!$B$33)-Допущения!$B$32-Допущения!$D$60-Допущения!$B$39 -> 19.49745 | H5: =G5/B5 -> 0.55786695 | I5: =B5-C5-B5*(Допущения!$B$34+Допущения!$E$17)-Допущения!$E$60 -> 11.625 | J5: =I5/B5 -> 0.33261803
A6: Magnesium Glycinate | B6: =Допущения!$C$61 -> 29.95 | C6: =Допущения!$K$61*Допущения!$E$19 -> 4.61 | D6: =Допущения!$M$61*Допущения!$E$19 -> 4.11 | E6: =B6-C6-B6*(Допущения!$B$26+Допущения!$B$29+Допущения!$B$30)-Допущения!$D$61-Допущения!$B$39 -> 7.0605 | F6: =E6/B6 -> 0.2357429 | G6: =B6-C6-B6*(Допущения!$B$31+Допущения!$B$33)-Допущения!$B$32-Допущения!$D$61-Допущения!$B$39 -> 17.57245 | H6: =G6/B6 -> 0.58672621 | I6: =B6-C6-B6*(Допущения!$B$34+Допущения!$E$17)-Допущения!$E$61 -> 10.955 | J6: =I6/B6 -> 0.36577629
A7: Creatine | B7: =Допущения!$C$62 -> 29.95 | C7: =Допущения!$K$62*Допущения!$E$19 -> 6.35 | D7: =Допущения!$M$62*Допущения!$E$19 -> 6.05 | E7: =B7-C7-B7*(Допущения!$B$26+Допущения!$B$29+Допущения!$B$30)-Допущения!$D$62-Допущения!$B$39 -> 3.3205 | F7: =E7/B7 -> 0.11086811 | G7: =B7-C7-B7*(Допущения!$B$31+Допущения!$B$33)-Допущения!$B$32-Допущения!$D$62-Допущения!$B$39 -> 13.83245 | H7: =G7/B7 -> 0.46185142 | I7: =B7-C7-B7*(Допущения!$B$34+Допущения!$E$17)-Допущения!$E$62 -> 8.065 | J7: =I7/B7 -> 0.26928214
A9: Первая покупка
A10: Предложение | B10: Цена | C10: Товар @1 000 | D10: Прибыль TikTok | E10: Прибыль Shopify | F10: Доля заказов
A11: =Допущения!A67 -> Foundation: Colostrum + Magnesium | B11: =Допущения!B67 -> 59.95 | C11: =Допущения!E67*Допущения!$K$59*Допущения!$E$19+Допущения!F67*Допущения!$K$60*Допущения!$E$19+Допущения!G67*Допущения!$K$61*Допущения!$E$19+Допущения!H67*Допущения!$K$62*Допущения!$E$19 -> 12.58 | D11: =B11-C11-B11*(Допущения!$B$26+Допущения!$B$29+Допущения!$B$30)-Допущения!C67-Допущения!$B$39 -> 14.7905 | E11: =B11-C11-B11*(Допущения!$B$31+Допущения!$B$33)-Допущения!$B$32-Допущения!C67-Допущения!$B$39 -> 36.13245 | F11: =Допущения!D67 -> 0.35
A12: =Допущения!A68 -> Gut Duo: Colostrum + Probiotic | B12: =Допущения!B68 -> 64.95 | C12: =Допущения!E68*Допущения!$K$59*Допущения!$E$19+Допущения!F68*Допущения!$K$60*Допущения!$E$19+Допущения!G68*Допущения!$K$61*Допущения!$E$19+Допущения!H68*Допущения!$K$62*Допущения!$E$19 -> 15.41 | D12: =B12-C12-B12*(Допущения!$B$26+Допущения!$B$29+Допущения!$B$30)-Допущения!C68-Допущения!$B$39 -> 14.9105 | E12: =B12-C12-B12*(Допущения!$B$31+Допущения!$B$33)-Допущения!$B$32-Допущения!C68-Допущения!$B$39 -> 38.05745 | F12: =Допущения!D68 -> 0.1
A13: =Допущения!A69 -> The Daily Four | B13: =Допущения!B69 -> 114.95 | C13: =Допущения!E69*Допущения!$K$59*Допущения!$E$19+Допущения!F69*Допущения!$K$60*Допущения!$E$19+Допущения!G69*Допущения!$K$61*Допущения!$E$19+Допущения!H69*Допущения!$K$62*Допущения!$E$19 -> 26.37 | D13: =B13-C13-B13*(Допущения!$B$26+Допущения!$B$29+Допущения!$B$30)-Допущения!C69-Допущения!$B$39 -> 30.4505 | E13: =B13-C13-B13*(Допущения!$B$31+Допущения!$B$33)-Допущения!$B$32-Допущения!C69-Допущения!$B$39 -> 71.64745 | F13: =Допущения!D69 -> 0.05
A14: =Допущения!A70 -> Colostrum | B14: =Допущения!B70 -> 39.95 | C14: =Допущения!E70*Допущения!$K$59*Допущения!$E$19+Допущения!F70*Допущения!$K$60*Допущения!$E$19+Допущения!G70*Допущения!$K$61*Допущения!$E$19+Допущения!H70*Допущения!$K$62*Допущения!$E$19 -> 7.97 | D14: =B14-C14-B14*(Допущения!$B$26+Допущения!$B$29+Допущения!$B$30)-Допущения!C70-Допущения!$B$39 -> 8.6005 | E14: =B14-C14-B14*(Допущения!$B$31+Допущения!$B$33)-Допущения!$B$32-Допущения!C70-Допущения!$B$39 -> 22.72245 | F14: =Допущения!D70 -> 0.2
A15: =Допущения!A71 -> Women's Probiotic | B15: =Допущения!B71 -> 34.95 | C15: =Допущения!E71*Допущения!$K$59*Допущения!$E$19+Допущения!F71*Допущения!$K$60*Допущения!$E$19+Допущения!G71*Допущения!$K$61*Допущения!$E$19+Допущения!H71*Допущения!$K$62*Допущения!$E$19 -> 7.44 | D15: =B15-C15-B15*(Допущения!$B$26+Допущения!$B$29+Допущения!$B$30)-Допущения!C71-Допущения!$B$39 -> 7.1805 | E15: =B15-C15-B15*(Допущения!$B$31+Допущения!$B$33)-Допущения!$B$32-Допущения!C71-Допущения!$B$39 -> 19.49745 | F15: =Допущения!D71 -> 0.12
A16: =Допущения!A72 -> Magnesium Glycinate | B16: =Допущения!B72 -> 29.95 | C16: =Допущения!E72*Допущения!$K$59*Допущения!$E$19+Допущения!F72*Допущения!$K$60*Допущения!$E$19+Допущения!G72*Допущения!$K$61*Допущения!$E$19+Допущения!H72*Допущения!$K$62*Допущения!$E$19 -> 4.61 | D16: =B16-C16-B16*(Допущения!$B$26+Допущения!$B$29+Допущения!$B$30)-Допущения!C72-Допущения!$B$39 -> 7.0605 | E16: =B16-C16-B16*(Допущения!$B$31+Допущения!$B$33)-Допущения!$B$32-Допущения!C72-Допущения!$B$39 -> 17.57245 | F16: =Допущения!D72 -> 0.1
A17: =Допущения!A73 -> Creatine | B17: =Допущения!B73 -> 29.95 | C17: =Допущения!E73*Допущения!$K$59*Допущения!$E$19+Допущения!F73*Допущения!$K$60*Допущения!$E$19+Допущения!G73*Допущения!$K$61*Допущения!$E$19+Допущения!H73*Допущения!$K$62*Допущения!$E$19 -> 6.35 | D17: =B17-C17-B17*(Допущения!$B$26+Допущения!$B$29+Допущения!$B$30)-Допущения!C73-Допущения!$B$39 -> 3.3205 | E17: =B17-C17-B17*(Допущения!$B$31+Допущения!$B$33)-Допущения!$B$32-Допущения!C73-Допущения!$B$39 -> 13.83245 | F17: =Допущения!D73 -> 0.08
A18: Средний первый заказ | B18: =SUMPRODUCT(B11:B17,F11:F17) -> 50.8 | D18: =SUMPRODUCT(D11:D17,F11:F17) -> 11.7437 | E18: =SUMPRODUCT(E11:E17,F11:F17) -> 29.7825
A20: Подписка Shopify
A21: Подписка | B21: Цена в месяц | C21: Товар @1 000 | D21: Прибыль в месяц | E21: Прибыль в год | F21: Доля | G21: Жизнь подписчика, мес. | H21: Прибыль за жизнь (LTV)
A22: =Допущения!A78 -> Foundation | B22: =Допущения!B78 -> 54.95 | C22: =Допущения!E78*Допущения!$K$59*Допущения!$E$19+Допущения!F78*Допущения!$K$60*Допущения!$E$19+Допущения!G78*Допущения!$K$61*Допущения!$E$19+Допущения!H78*Допущения!$K$62*Допущения!$E$19 -> 12.58 | D22: =B22-C22-B22*(Допущения!$B$31+Допущения!$B$33)-Допущения!$B$32-Допущения!C78-Допущения!$B$39 -> 31.37745 | E22: =D22*12 -> 376.5294 | F22: =Допущения!D78 -> 0.6 | G22: =1/Допущения!$E$12 -> 10 | H22: =D22*G22 -> 313.7745
A23: =Допущения!A79 -> Gut Duo | B23: =Допущения!B79 -> 59.95 | C23: =Допущения!E79*Допущения!$K$59*Допущения!$E$19+Допущения!F79*Допущения!$K$60*Допущения!$E$19+Допущения!G79*Допущения!$K$61*Допущения!$E$19+Допущения!H79*Допущения!$K$62*Допущения!$E$19 -> 15.41 | D23: =B23-C23-B23*(Допущения!$B$31+Допущения!$B$33)-Допущения!$B$32-Допущения!C79-Допущения!$B$39 -> 33.30245 | E23: =D23*12 -> 399.6294 | F23: =Допущения!D79 -> 0.25 | G23: =1/Допущения!$E$12 -> 10 | H23: =D23*G23 -> 333.0245
A24: =Допущения!A80 -> The Daily Four, креатин раз в 2 мес. | B24: =Допущения!B80 -> 99.95 | C24: =Допущения!E80*Допущения!$K$59*Допущения!$E$19+Допущения!F80*Допущения!$K$60*Допущения!$E$19+Допущения!G80*Допущения!$K$61*Допущения!$E$19+Допущения!H80*Допущения!$K$62*Допущения!$E$19 -> 23.195 | D24: =B24-C24-B24*(Допущения!$B$31+Допущения!$B$33)-Допущения!$B$32-Допущения!C80-Допущения!$B$39 -> 61.55745 | E24: =D24*12 -> 738.6894 | F24: =Допущения!D80 -> 0.15 | G24: =1/Допущения!$E$12 -> 10 | H24: =D24*G24 -> 615.5745
A25: Средний подписчик | B25: =SUMPRODUCT(B22:B24,F22:F24) -> 62.95 | D25: =SUMPRODUCT(D22:D24,F22:F24) -> 36.3857 | E25: =SUMPRODUCT(E22:E24,F22:F24) -> 436.6284 | G25: =1/Допущения!$E$12 -> 10 | H25: =SUMPRODUCT(H22:H24,F22:F24) -> 363.857
A27: Ценность одного криейтора в месяц
A28: Заказов с роликов и органики | B28: =Допущения!$B$23*Допущения!$E$8*Допущения!$E$6*Допущения!$E$7*(1+Допущения!$E$9) -> 24
A29: Продаж на сумму | B29: =B28*Допущения!$B$74 -> 1219.2
A30: Заработок криейтора | B30: =B29*Допущения!$B$29 -> 365.76
A31: Заработок криейтора за ролик | B31: =B30/(Допущения!$B$23*Допущения!$E$8) -> 45.72
A32: Прибыль бренда с первых покупок | B32: =B28*D18 -> 281.8488
A33: Новых подписчиков | B33: =B28*(1+Допущения!$E$10)*Допущения!$E$11 -> 3.96
A34: Прибыль с этих подписчиков за их жизнь | B34: =B33*H25 -> 1440.8737

Sheet Сценарии
A1: Три сценария
A2: Снимок расчёта от 03.10.2026 по базовым вводным. После изменения допущений пересчитать: python3 analysis.py && python3 stress.py && python3 build_analysis_sheets.py
A4: Показатель | B4: Консервативный | C4: Базовый | D4: Оптимистичный
A5: Выручка год 1 | B5: 756747.27 | C5: 3677785.5 | D5: 11026826
A6: EBITDA год 1 | B6: 130137.95 | C6: 1188083.3 | D6: 4299386.1
A7: Выручка год 2 | B7: 1943383.1 | C7: 12077196 | D7: 43391967
A8: EBITDA год 2 | B8: 345631.75 | C8: 4600647.7 | D8: 19458257
A9: Выручка год 3 | B9: 2940438.7 | C9: 21146706 | D9: 72554176
A10: EBITDA год 3 | B10: 676029.56 | C10: 8729180 | D10: 35217566
A11: Чистая прибыль 3 года (сумма) | B11: 863849.44 | C11: 10888433 | D11: 44231407
A12: Подписчиков через 12 мес. | B12: 430.05174 | C12: 3893.9825 | D12: 16838.876
A13: Подписчиков через 24 мес. | B13: 912.83776 | C13: 10187.6 | D13: 49988.822
A14: Криейторов через 24 мес. | B14: 172 | C14: 294 | D14: 400
A15: Деньги на счёте через 12 мес. | B15: 61633.232 | C15: 624408.93 | D15: 2393394.4
A16: Минимум денег на счёте | B16: 245 | C16: -8323.2387 | D16: -42794.027
A17: Месяц темпа $1 млн EBITDA в год | B17: нет за 36 мес. | C17: 7 | D17: 3
A18: Окупаемость $25 000, месяц | B18: 6 | C18: 2 | D18: 2
A20: Что отличает сценарии
A21: Параметр | B21: Консервативный | C21: Базовый | D21: Оптимистичный
A22: Просмотров на ролик | B22: 3 500 | C22: 5 000 | D22: 7 000
A23: Конверсия | B23: 0,03% | C23: 0,05% | D23: 0,07%
A24: Доля вышедших роликов | B24: 60% | C24: 100% | D24: 100%
A25: Переход в подписку | B25: 12% | C25: 15% | D25: 20%
A26: Отток подписки | B26: 12% | C26: 10% | D26: 8%
A27: Новых криейторов в мес. | B27: 5-6 | C27: 10-12 | D27: 15-18
A28: Amazon, продаж в день на продукт | B28: 13 | C28: 30 | D28: 45
A29: Spark Ads, выручка на $1 рекламы | B29: 2 | C29: 3 | D29: 4
A30: Цена Vox | B30: +5% | C30: прайс | D30: прайс
A32: Деньги на старте: варианты финансирования (базовый сценарий)
A33: Вариант | B33: Минимум денег | C33: Месяц минимума | D33: EBITDA год 1
A34: Транш 2 = $5 000, запас 1,3 мес. | B34: -8323.2387 | C34: 2 | D34: 1188083.3
A35: Транш 2 = $5 000, запас 1,0 мес. | B35: -1157.7387 | C35: 2 | D35: 1188083.3
A36: Транш 2 = $14 000, запас 1,3 мес. | B36: 245 | C36: 0 | D36: 1188083.3
A37: Транш 2 = $21 000, запас 1,3 мес. | B37: 245 | C37: 0 | D37: 1188083.3

Sheet Чувствительность
A1: Чувствительность и стресс-тесты
A2: Снимок расчёта от 03.10.2026 по базовым вводным. После изменения допущений пересчитать: python3 analysis.py && python3 stress.py && python3 build_analysis_sheets.py
A4: Торнадо: каждый параметр отдельно, остальное по базе
A5: Параметр | B5: Плохое значение | C5: Хорошее значение | D5: EBITDA год 1, плохо | E5: EBITDA год 1, хорошо | F5: EBITDA год 2, плохо | G5: EBITDA год 2, хорошо | H5: Размах год 2
A6: Конверсия просмотра в заказ | B6: 0.0003 | C6: 0.0007 | D6: 754570.91 | E6: 1630402.9 | F6: 2892576.2 | G6: 6294933.3 | H6: 3402357.1
A7: Просмотров на ролик | B7: 3500 | C7: 7000 | D7: 860953.76 | E7: 1630402.9 | F7: 3322165.9 | G7: 6294933.3 | H7: 2972767.4
A8: Новых криейторов в мес. 3-12 | B8: 5 | C8: 15 | D8: 952202.31 | E8: 1424715.5 | F8: 3553357.7 | G8: 5644751.3 | H8: 2091393.6
A9: Доля вышедших роликов | B9: 0.6 | C9: 1 | D9: 754570.91 | E9: 1188083.3 | F9: 2892576.2 | G9: 4600647.7 | H9: 1708071.5
A10: Переход в подписку | B10: 0.12 | C10: 0.2 | D10: 1052786.4 | E10: 1409732.9 | F10: 3972667.1 | G10: 5651050.1 | H10: 1678383
A11: Новых криейторов в мес. с 13-го | B11: 6 | C11: 18 | D11: 1188083.3 | E11: 1188083.3 | F11: 4145540.9 | G11: 5059628 | H11: 914087.03
A12: Органика | B12: 0.1 | C12: 0.3 | D12: 1095859.3 | E12: 1276662.2 | F12: 4247420 | G12: 4958997.1 | H12: 711577.1
A13: Spark Ads: ROAS | B13: 2 | C13: 4 | D13: 1107948.6 | E13: 1264925 | F13: 4254976.7 | G13: 4952828.7 | H13: 697852.01
A14: Отток подписки | B14: 0.12 | C14: 0.08 | D14: 1156405.2 | E14: 1220556.9 | F14: 4331392.5 | G14: 4920566.4 | H14: 589173.84
A15: Amazon: продаж в день на продукт | B15: 13 | C15: 45 | D15: 1077048.1 | E15: 1282787.9 | F15: 4304478.7 | G15: 4869139.1 | H15: 564660.45
A16: Комиссия криейтора | B16: 0.35 | C16: 0.25 | D16: 1100814 | E16: 1275352.6 | F16: 4378357.1 | G16: 4822938.3 | H16: 444581.28
A17: Цена Vox | B17: 1.1 | C17: 0.95 | D17: 1111419.2 | E17: 1226415.4 | F17: 4363270.1 | G17: 4719336.5 | H17: 356066.45
A18: Amazon: доля рекламы | B18: 0.2 | C18: 0.12 | D18: 1156061.2 | E18: 1207296.6 | F18: 4497719.4 | G18: 4662404.7 | H18: 164685.31
A20: Стресс-тесты
A21: Событие | B21: EBITDA год 1 | C21: EBITDA год 2 | D21: EBITDA год 3 | E21: Минимум денег | F21: Темп $1 млн, месяц
A22: Базовый сценарий | B22: 1188083.3 | C22: 4600647.7 | D22: 8729180 | E22: -8323.2387 | F22: 7
A23: TikTok Shop заблокирован на 2 месяца (март-апрель 2027) | B23: 964428.11 | C23: 4478670.5 | D23: 8694880.2 | E23: -8323.2387 | F23: 8
A24: Vox не отгрузил товар: месяц без продаж (февраль 2027) | B24: 1145351.4 | C24: 4600647.7 | D24: 8729180 | E24: -8323.2387 | F24: 7
A25: Amazon не дал допуск к категории | B25: 965450.38 | C25: 3874085.2 | D25: 7693194.7 | E25: -8323.2387 | F25: 8
A26: Продукт не цепляет: конверсия 0,02% | B26: 542945.43 | C26: 2040521.9 | D26: 3891315.5 | E26: 245 | F26: 11
A27: Криейторов не прибавляется: 50 весь срок | B27: 724338.12 | C27: 1590577.4 | D27: 2034233.7 | E27: -4644.7387 | F27: 9
A28: Цены Vox +15% | B28: 1073087.2 | C28: 4244581.3 | D28: 8110459.8 | E28: -13149.34 | F28: 7
A29: Spark Ads не окупаются: ROAS 1,5 | B29: 1068999.2 | C29: 4080301.4 | D29: 7739418 | E29: -8323.2387 | F29: 7
A30: TikTok оставил комиссию 6% | B30: 1222991 | C30: 4689564 | D30: 8872162.4 | E30: -7587.1467 | F30: 7
A31: Подписка не работает: переход 5%, отток 15% | B31: 714769.16 | C31: 2289581.6 | D31: 4021051.4 | E31: -5535.5891 | F31: 9
A32: Всё плохо сразу: конверсия 0,03%, 60% роликов, без Amazon, отток 12% | B32: 231627.78 | C32: 876943.57 | D32: 1847410.3 | E32: 245 | F32: 21
A34: Точки безубыточности по конверсии (без Amazon, остальное по базе)
A35: EBITDA года 1 больше нуля при конверсии от | B35: 4.0972081e-05
A36: EBITDA года 2 от $1 млн при конверсии от | B36: 0.0001588523
A37: EBITDA года 1 от $1 млн при конверсии от | B37: 0.00051634169
A38: База: 0,05%. Запас прочности по конверсии большой: бизнес остаётся прибыльным, даже если конверсия в 10 раз ниже базы.

Sheet Монте-Карло
A1: Монте-Карло: 5000 случайных прогонов модели
A2: Снимок расчёта от 03.10.2026 по базовым вводным. После изменения допущений пересчитать: python3 analysis.py && python3 stress.py && python3 build_analysis_sheets.py Сид 42.
A4: Распределения вводных (треугольные: минимум, наиболее вероятное, максимум)
A5: Параметр | B5: Минимум | C5: Наиболее вероятное | D5: Максимум
A6: Просмотров на ролик | B6: 3000 | C6: 5000 | D6: 8000
A7: Конверсия | B7: 0.0002 | C7: 0.0005 | D7: 0.0008
A8: Доля вышедших роликов | B8: 0.5 | C8: 0.85 | D8: 1
A9: Органика | B9: 0.05 | C9: 0.2 | D9: 0.3
A10: Прямые заказы Shopify | B10: 0.05 | C10: 0.1 | D10: 0.15
A11: Переход в подписку | B11: 0.08 | C11: 0.15 | D11: 0.22
A12: Отток подписки | B12: 0.07 | C12: 0.1 | D12: 0.15
A13: Новых криейторов мес. 3-12 | B13: 4 | C13: 10 | D13: 15
A14: Новых криейторов с 13-го | B14: 5 | C14: 12 | D14: 18
A15: Amazon, продаж в день на продукт | B15: 8 | C15: 30 | D15: 45
A16: Amazon, прирост в день в мес. | B16: 0 | C16: 1.5 | D16: 2.5
A17: Amazon, доля рекламы | B17: 0.12 | C17: 0.15 | D17: 0.25
... A19: Множитель цены Vox | B19: 0.95 | C19: 1 | D19: 1.15
A21: Результаты
A22: Показатель | B22: P10 (плохой из 10) | C22: P50 (медиана) | D22: P90 (хороший из 10) | E22: Среднее
A23: Выручка год 1 | B23: 1973048.4 | C23: 2922730.7 | D23: 4325167.1 | E23: 3068876
A24: EBITDA год 1 | B24: 547050.6 | C24: 875237.98 | D24: 1390899.7 | E24: 934413.09
A25: Выручка год 2 | B25: 6257575.7 | C25: 9453852.3 | D25: 14281265 | E25: 9924719.6
A26: EBITDA год 2 | B26: 2008397.7 | C26: 3342876.3 | D26: 5407218.6 | E26: 3568252
A27: Выручка год 3 | B27: 10445827 | C27: 16176290 | D27: 24664742 | E27: 17008093
A28: EBITDA год 3 | B28: 3752836.9 | C28: 6309639.6 | D28: 10235314 | E28: 6724560.2
A29: Подписчиков через 24 мес. | B29: 4132.3157 | C29: 7443.7864 | D29: 12750.622 | E29: 8044.0474
A30: Минимум денег на счёте | B30: -15508.117 | C30: -3151.2067 | D30: 245 | E30: -5584.3987
A32: Вероятности
A33: EBITDA года 1 в минусе | B33: 0
A34: EBITDA года 1 от $1 млн | B34: 0.3618
A35: EBITDA года 2 от $1 млн | B35: 0.9996
A36: Темп $1 млн EBITDA в год наступает в первые 24 месяца | B36: 1
A37: Денег на старте не хватает без доплаты | B37: 0.6772
A38: Не хватает больше $10 000 | B38: 0.2256
A39: Нужная доплата с вероятностью 90% | B39: 15508.117
A40: Месяц темпа $1 млн: медиана | B40: 8
A41: Месяц темпа $1 млн: P10-P90 | B41: 6-11
A43: Распределение EBITDA года 2
A44: Диапазон | B44: Доля прогонов
A45: убыток | B45: 0
A46: $0-0,5 млн | B46: 0
A47: $0,5-1 млн | B47: 0.0004
A48: $1-2 млн | B48: 0.0986
A49: $2-3 млн | B49: 0.2938
A50: $3-4 млн | B50: 0.2864
A51: $4-5 млн | B51: 0.1724
A52: больше $5 млн | B52: 0.1484

Sheet Риски
A1: Реестр рисков
A2: Вероятность это оценка на 03.10.2026. Ущерб: потеря EBITDA года 1 из стресс-тестов и торнадо. Ожидаемый ущерб = вероятность × ущерб.
A4: Риск | B4: Вероятность | C4: Ущерб, EBITDA год 1 | D4: Ожидаемый ущерб | E4: Ранний сигнал (KPI) | F4: Что делаем | G4: Кто
A5: Криейторы не выпускают 8 роликов | B5: 0.5 | C5: 433512.4 | D5: =B5*C5 -> 216756.2 | E5: меньше 2 роликов в неделю на криейтора | F5: еженедельный учёт, замена неактивных, бонус лучшим | G5: Полина
A6: Конверсия ниже базы (0,03%) | B6: 0.3 | C6: 433512.4 | D6: =B6*C6 -> 130053.72 | E6: меньше 0,4 заказа на 1 000 просмотров в первые 2 недели | F6: тест хуков, Flip the jar, стартовая скидка | G6: владелец, Полина
A7: Подписка слабее плана | B7: 0.25 | C7: 473314.16 | D7: =B7*C7 -> 118328.54 | E7: переход в подписку меньше 10% за первые 60 дней | F7: письма день 0, 7, 25, скидка на первую подписку, вкладыш | G7: Claude, владелец
A8: Amazon не даёт допуск к добавкам | B8: 0.2 | C8: 222632.94 | D8: =B8*C8 -> 44526.587 | E8: нет допуска к 15.02.2027 | F8: COA из лаборатории ISO 17025 в январе, Brand Registry по заявке USPTO | G8: владелец
A9: Криейторов не прибавляется | B9: 0.2 | C9: 463745.19 | D9: =B9*C9 -> 92749.038 | E9: меньше 8 новых в месяц | F9: аутрич 100 в неделю, менеджер криейторов с 5-го месяца | G9: Полина
A10: TikTok Shop блокирует магазин на 2 месяца | B10: 0.1 | C10: 223655.2 | D10: =B10*C10 -> 22365.52 | E10: страйки за заявления, жалобы | F10: этикетка завода дословно, без заявлений о болезни, Shopify и Amazon как опора | G10: Claude
A11: Цены Vox растут на 15% | B11: 0.15 | C11: 114996.11 | D11: =B11*C11 -> 17249.417 | E11: новый прайс Vox | F11: годовой объём под цену, SMP вторым источником | G11: владелец
A12: Vox срывает отгрузку на месяц | B12: 0.15 | C12: 42731.894 | D12: =B12*C12 -> 6409.7841 | E12: срок перезаказа больше 15 рабочих дней | F12: запас 1,3 месяца, подтверждение мощности в мае 2027, SMP в резерве | G12: Claude
A13: Денег на товар не хватает в декабре | B13: 0.85 | C13: 8593.7 | D13: =B13*C13 -> 7304.645 | E13: деньги на счёте меньше $3 000 | F13: второй транш $21 000 или перезаказ дважды в месяц | G13: владелец
A14: Задержка выплат TikTok новому продавцу | B14: 0.3 | C14: 0 | D14: =B14*C14 -> 0 | E14: выплата позже 14 дней после доставки | F14: резерв в кассе, Shopify как быстрый канал денег | G14: владелец
A15: Претензия по качеству или отзыв партии | B15: 0.05 | C15: 50000 | D15: =B15*C15 -> 2500 | E15: жалобы на вкус, комки, реакции | F15: COA каждой партии, страховка ответственности, этикетка завода | G15: владелец
A16: Нагрузка на владельца и Полину | B16: 0.4 | C16: 0 | D16: =B16*C16 -> 0 | E16: ответ клиенту дольше 24 часов | F16: найм с 5-6-го месяца по плану команды | G16: владелец
A17: Итого ожидаемый ущерб | D17: =SUM(D5:D16) -> 658243.45

Sheet Допущения
A1: The Aldera · 518 GROUP LLC · Финансовая модель · допущения
A2: Синий шрифт: вводные, их можно менять. Чёрный: формулы. Жёлтая заливка: ключевые рычаги. Модель пересчитывается сама.
A3: Сценарий: 1 консервативный, 2 базовый, 3 оптимистичный | B3: 2
A5: Параметр сценария | B5: Консерв. | C5: Базовый | D5: Оптим. | E5: Активное | F5: Пояснение
A6: Просмотров на ролик | B6: 3500 | C6: 5000 | D6: 7000 | E6: =CHOOSE($B$3,B6,C6,D6) -> 5000 | F6: Средние просмотры ролика микро-криейтора
A7: Конверсия просмотра в заказ | B7: 0.0003 | C7: 0.0005 | D7: 0.0007 | E7: =CHOOSE($B$3,B7,C7,D7) -> 0.0005 | F7: Доля просмотров, которая становится заказом
A8: Доля роликов, которые реально выходят | B8: 0.6 | C8: 1 | D8: 1 | E8: =CHOOSE($B$3,B8,C8,D8) -> 1 | F8: 8 роликов по договору; база по условию владельца
A9: Органика и поиск сверху | B9: 0.1 | C9: 0.2 | D9: 0.3 | E9: =CHOOSE($B$3,B9,C9,D9) -> 0.2 | F9: Заказы без ролика: поиск, профиль, повторный показ
A10: Прямые заказы на Shopify, доля от TikTok | B10: 0.05 | C10: 0.1 | D10: 0.15 | E10: =CHOOSE($B$3,B10,C10,D10) -> 0.1 | F10: Покупатели из TikTok, которые идут на сайт
A11: Переход первых покупателей в подписку | B11: 0.12 | C11: 0.15 | D11: 0.2 | E11: =CHOOSE($B$3,B11,C11,D11) -> 0.15 | F11: Главный рычаг модели
A12: Отток подписки в месяц | B12: 0.12 | C12: 0.1 | D12: 0.08 | E12: =CHOOSE($B$3,B12,C12,D12) -> 0.1 | F12: Обычная цифра для подписки на добавки около 10%
A13: Новых криейторов в месяц, мес. 3-12 | B13: 5 | C13: 10 | D13: 15 | E13: =CHOOSE($B$3,B13,C13,D13) -> 10 | F13: Старт 50 криейторов
A14: Новых криейторов в месяц, с 13-го | B14: 6 | C14: 12 | D14: 18 | E14: =CHOOSE($B$3,B14,C14,D14) -> 12
A15: Amazon: продаж в день на продукт после разгона | B15: 13 | C15: 30 | D15: 45 | E15: =CHOOSE($B$3,B15,C15,D15) -> 30 | F15: Достигается через N месяцев разгона
A16: Amazon: прирост в день на продукт в месяц после разгона | B16: 0.5 | C16: 1.5 | D16: 2.5 | E16: =CHOOSE($B$3,B16,C16,D16) -> 1.5
A17: Amazon: реклама PPC, доля цены | B17: 0.2 | C17: 0.15 | D17: 0.12 | E17: =CHOOSE($B$3,B17,C17,D17) -> 0.15 | F17: Половина продаж через рекламу при ACoS 24-40%
A18: Spark Ads: выручка на $1 рекламы (ROAS) | B18: 2 | C18: 3 | D18: 4 | E18: =CHOOSE($B$3,B18,C18,D18) -> 3 | F18: Реклама идёт только на ролики с доказанной конверсией
A19: Множитель себестоимости Vox | B19: 1.05 | C19: 1 | D19: 1 | E19: =CHOOSE($B$3,B19,C19,D19) -> 1 | F19: Рост цен поставщика
A21: Постоянные допущения
A22: Криейторов на старте | B22: 50 | C22: Решение владельца
A23: Роликов на криейтора в месяц по договору | B23: 8 | C23: Решение владельца: 8 роликов за 30%
A24: Потолок числа криейторов | B24: 400 | C24: Предел для одного менеджера-отдела
A25: Доля первого месяца (продажи с 20.11) | B25: 0.36666667 | C25: 11 дней из 30
A26: TikTok Shop: комиссия площадки | B26: 0.08 | C26: С 04.08.2026 TikTok поднял ставку с 6% до 8% для большинства непищевых категорий. Ставку для добавок проверить в Seller Center
A27: Spark Ads на выстрелившие ролики, доля органической выручки TikTok | B27: 0.1 | C27: Решение владельца 03.10: платная реклама только на ролики, которые уже выстрелили
A28: Spark Ads: с месяца модели | B28: 4 | C28: Февраль 2027: после декабрьского провала денег
A29: Комиссия криейтора | B29: 0.3 | C29: Решение владельца
A30: TikTok: возвраты, доля выручки | B30: 0.03
A31: Shopify Payments: процент | B31: 0.029 | C31: Тариф Shopify Basic
A32: Shopify Payments: за транзакцию | B32: 0.3
A33: Shopify: возвраты, доля выручки | B33: 0.02
A34: Amazon: комиссия за продажу | B34: 0.15 | C34: Категория Health & Household
A35: Amazon: месяц старта (1 = ноябрь 2026) | B35: 5 | C35: Март 2027, после Brand Registry и допуска
A36: Amazon: продаж в день на продукт в первый месяц | B36: 5
A37: Amazon: месяцев разгона | B37: 6
A38: Число продуктов | B38: 4
A39: Склад-отправщик, за заказ TikTok и Shopify | B39: 2.5 | C39: Пик-пак 3PL во Флориде, оценка
A40: Доля выплат TikTok и Amazon, приходящая в следующем месяце | B40: 0.5 | C40: Выплаты после доставки и раз в две недели
A41: Запас товара после перезаказа, месяцев продаж | B41: 1.3 | C41: Политика перезаказа
A42: Минимальный заказ Vox, банок | B42: 150 | C42: Прайс Vox 2026 Q3
A43: Сервисы и ПО в месяц, год 1 | B43: 500 | C43: Shopify, подписка, почта, дизайн-сервисы
A44: Сервисы и ПО в месяц, год 2 | B44: 1000
A45: Сервисы и ПО в месяц, год 3 | B45: 1500
A46: Страховка ответственности в месяц, первые 11 мес. | B46: 150 | C46: Product liability
A47: Страховка ответственности в месяц, с 12-го | B47: 500 | C47: Amazon требует при продажах от $10 тыс. в месяц
A48: Бухгалтерия и юристы в месяц | B48: 300
A49: Прочая реклама (Meta, Google), доля выручки | B49: 0 | C49: Не планируется; 0 = не включено
A50: Налог на прибыль, оценка | B50: 0.25 | C50: Оценка: федеральный и штатный налог на прибыль LLC через владельца. Уточнить у бухгалтера
A51: Вложение владельца, транш 1 (октябрь 2026) | B51: 20000 | C51: Решение владельца 03.10
A52: Вложение владельца, транш 2 (конец ноября 2026) | B52: 5000 | C52: Решение владельца 03.10: партиями
A53: Запуск: дизайн 4 этикеток, GS1, фрахт, образцы | B53: 2249 | C53: $499 + $300 + $500 + $950
A54: Заявка USPTO на знак THE ALDERA, класс 5 | B54: 350 | C54: Пошлина USPTO за 1 класс
A56: Продукты (Vox Nutrition, сток, минимум 150)
A57: Продукт | B57: Артикул Vox | C57: Розница | D57: Доставка 1 банки | E57: FBA за банку | F57: Доля в Amazon | G57: Первая закупка, банок | H57: Цена @150 | I57: Цена @300 | J57: Цена @500 | K57: Цена @1000 | L57: Цена @2500 | M57: Цена @5000 | N57: Цена @7500 | O57: Цена @10000
A58: Порог ступени, банок | H58: 150 | I58: 300 | J58: 500 | K58: 1000 | L58: 2500 | M58: 5000 | N58: 7500 | O58: 10000
A59: Colostrum | B59: 14721 | C59: 39.95 | D59: 4.5 | E59: 6.55 | F59: 0.35 | G59: 1000 | H59: 8.52 | I59: 8.37 | J59: 8.12 | K59: 7.97 | L59: 7.82 | M59: 7.67 | N59: 7.42 | O59: 7.12
A60: Women's Probiotic | B60: 14648 | C60: 34.95 | D60: 3.5 | E60: 5.4 | F60: 0.15 | G60: 400 | H60: 8.34 | I60: 7.99 | J60: 7.64 | K60: 7.44 | L60: 7.24 | M60: 6.94 | N60: 6.74 | O60: 6.59
A61: Magnesium Glycinate | B61: 14683 | C61: 29.95 | D61: 3.5 | E61: 5.4 | F61: 0.25 | G61: 1000 | H61: 5.51 | I61: 5.16 | J61: 4.81 | K61: 4.61 | L61: 4.41 | M61: 4.11 | N61: 3.91 | O61: 3.76
A62: Creatine | B62: 14589 | C62: 29.95 | D62: 5.5 | E62: 6.55 | F62: 0.25 | G62: 200 | H62: 6.9 | I62: 6.75 | J62: 6.5 | K62: 6.35 | L62: 6.2 | M62: 6.05 | N62: 5.8 | O62: 5.5
A63: Источник цен: прайс Vox Nutrition 2026 Q3 Pricing Sheet. Розница: решение по позиционированию 03.10. Креатин в первой закупке 200, чтобы транш $20 000 покрыл и заявку на знак.
A65: Первая покупка: предложения и доли заказов
A66: Предложение | B66: Цена | C66: Доставка заказа | D66: Доля заказов | E66: Colostrum, банок | F66: Probiotic, банок | G66: Magnesium, банок | H66: Creatine, банок
A67: Foundation: Colostrum + Magnesium | B67: 59.95 | C67: 5.5 | D67: 0.35 | E67: 1 | F67: 0 | G67: 1 | H67: 0
A68: Gut Duo: Colostrum + Probiotic | B68: 64.95 | C68: 5.5 | D68: 0.1 | E68: 1 | F68: 1 | G68: 0 | H68: 0
A69: The Daily Four | B69: 114.95 | C69: 8.5 | D69: 0.05 | E69: 1 | F69: 1 | G69: 1 | H69: 1
A70: Colostrum | B70: 39.95 | C70: 4.5 | D70: 0.2 | E70: 1 | F70: 0 | G70: 0 | H70: 0
A71: Women's Probiotic | B71: 34.95 | C71: 3.5 | D71: 0.12 | E71: 0 | F71: 1 | G71: 0 | H71: 0
A72: Magnesium Glycinate | B72: 29.95 | C72: 3.5 | D72: 0.1 | E72: 0 | F72: 0 | G72: 1 | H72: 0
A73: Creatine | B73: 29.95 | C73: 5.5 | D73: 0.08 | E73: 0 | F73: 0 | G73: 0 | H73: 1
A74: Средний первый заказ | B74: =SUMPRODUCT(B67:B73,$D$67:$D$73) -> 50.8 | C74: =SUMPRODUCT(C67:C73,$D$67:$D$73) -> 5.01 | D74: =SUM(D67:D73) -> 1 | E74: =SUMPRODUCT(E67:E73,$D$67:$D$73) -> 0.7 | F74: =SUMPRODUCT(F67:F73,$D$67:$D$73) -> 0.27 | G74: =SUMPRODUCT(G67:G73,$D$67:$D$73) -> 0.5 | H74: =SUMPRODUCT(H67:H73,$D$67:$D$73) -> 0.13 | I74: ← банок каждого продукта на один средний заказ
A76: Подписка Shopify, ежемесячно
A77: Подписка | B77: Цена в месяц | C77: Доставка | D77: Доля подписчиков | E77: Colostrum, банок | F77: Probiotic, банок | G77: Magnesium, банок | H77: Creatine, банок
A78: Foundation | B78: 54.95 | C78: 5.5 | D78: 0.6 | E78: 1 | F78: 0 | G78: 1 | H78: 0
A79: Gut Duo | B79: 59.95 | C79: 5.5 | D79: 0.25 | E79: 1 | F79: 1 | G79: 0 | H79: 0
A80: The Daily Four, креатин раз в 2 мес. | B80: 99.95 | C80: 7.5 | D80: 0.15 | E80: 1 | F80: 1 | G80: 1 | H80: 0.5
A81: Средний подписчик | B81: =SUMPRODUCT(B78:B80,$D$78:$D$80) -> 62.95 | C81: =SUMPRODUCT(C78:C80,$D$78:$D$80) -> 5.8 | D81: =SUM(D78:D80) -> 1 | E81: =SUMPRODUCT(E78:E80,$D$78:$D$80) -> 1 | F81: =SUMPRODUCT(F78:F80,$D$78:$D$80) -> 0.4 | G81: =SUMPRODUCT(G78:G80,$D$78:$D$80) -> 0.75 | H81: =SUMPRODUCT(H78:H80,$D$78:$D$80) -> 0.075
A83: Amazon: средняя цена заказа | B83: =SUMPRODUCT(C59:C62,F59:F62) -> 34.2
A84: Amazon: средний FBA за заказ | B84: =SUMPRODUCT(E59:E62,F59:F62) -> 6.09
A86: Сезонность по календарным месяцам
A87: январь | B87: 1.1 | C87: Black Friday и праздники +15%, январь (новогодние цели) +10%
A88: февраль | B88: 1
A89: март | B89: 1
A90: апрель | B90: 1
A91: май | B91: 1
A92: июнь | B92: 1
A93: июль | B93: 1
A94: август | B94: 1
A95: сентябрь | B95: 1
A96: октябрь | B96: 1
A97: ноябрь | B97: 1.15
A98: декабрь | B98: 1.15
A100: Команда (найм по месяцам модели)
A101: Роль | B101: Стоимость в месяц | C101: С месяца модели
A102: Менеджер криейторов 1 | B102: 4000 | C102: 5 | D102: Месяц 1 = ноябрь 2026. Зарплата владельца не заложена.
A103: Поддержка клиентов | B103: 3000 | C103: 6
A104: Менеджер Amazon и операций | B104: 5000 | C104: 10
A105: Менеджер криейторов 2 | B105: 4000 | C105: 13
A106: Поддержка клиентов 2 | B106: 3000 | C106: 16
A107: Финансы, на аутсорсе | B107: 2000 | C107: 18

Sheet Модель
A1: Помесячная модель, 36 месяцев (ноябрь 2026 - октябрь 2029)
A2: Месяц модели | C2: 0 | D2: =C2+1 -> 1 | E2: =D2+1 -> 2 | F2: =E2+1 -> 3 | G2: =F2+1 -> 4 | H2: =G2+1 -> 5 | I2: =H2+1 -> 6 | J2: =I2+1 -> 7 | K2: =J2+1 -> 8 | ... AM2: =AL2+1 -> 36
A3: Месяц | C3: =DATE(2026,10+C2,1) -> 46296 | D3: =DATE(2026,10+D2,1) -> 46327 | E3: =DATE(2026,10+E2,1) -> 46357 | F3: =DATE(2026,10+F2,1) -> 46388 | G3: =DATE(2026,10+G2,1) -> 46419 | H3: =DATE(2026,10+H2,1) -> 46447 | I3: =DATE(2026,10+I2,1) -> 46478 | J3: =DATE(2026,10+J2,1) -> 46508 | ... AM3: =DATE(2026,10+AM2,1) -> 47392
A4: Календарный месяц | C4: =MONTH(C3) -> 10 | D4: =MONTH(D3) -> 11 | E4: =MONTH(E3) -> 12 | F4: =MONTH(F3) -> 1 | G4: =MONTH(G3) -> 2 | H4: =MONTH(H3) -> 3 | I4: =MONTH(I3) -> 4 | J4: =MONTH(J3) -> 5 | ... AM4: =MONTH(AM3) -> 10
A5: Год модели | C5: =IF(C2=0,0,INT((C2-1)/12)+1) -> 0 | D5: =IF(D2=0,0,INT((D2-1)/12)+1) -> 1 | E5: =IF(E2=0,0,INT((E2-1)/12)+1) -> 1 | F5: =IF(F2=0,0,INT((F2-1)/12)+1) -> 1 | G5: =IF(G2=0,0,INT((G2-1)/12)+1) -> 1 | H5: =IF(H2=0,0,INT((H2-1)/12)+1) -> 1 | I5: =IF(I2=0,0,INT((I2-1)/12)+1) -> 1 | J5: =IF(J2=0,0,INT((J2-1)/12)+1) -> 1 | ... AM5: =IF(AM2=0,0,INT((AM2-1)/12)+1) -> 3
A6: Доля месяца | C6: =IF(C2=0,0,IF(C2=1,Допущения!$B$25,1)) -> 0 | D6: =IF(D2=0,0,IF(D2=1,Допущения!$B$25,1)) -> 0.36666667 | E6: =IF(E2=0,0,IF(E2=1,Допущения!$B$25,1)) -> 1 | F6: =IF(F2=0,0,IF(F2=1,Допущения!$B$25,1)) -> 1 | G6: =IF(G2=0,0,IF(G2=1,Допущения!$B$25,1)) -> 1 | H6: =IF(H2=0,0,IF(H2=1,Допущения!$B$25,1)) -> 1 | I6: =IF(I2=0,0,IF(I2=1,Допущения!$B$25,1)) -> 1 | J6: =IF(J2=0,0,IF(J2=1,Допущения!$B$25,1)) -> 1 | ... AM6: =IF(AM2=0,0,IF(AM2=1,Допущения!$B$25,1)) -> 1
A7: Сезонность | C7: =INDEX(Допущения!$B$87:$B$98,C4) -> 1 | D7: =INDEX(Допущения!$B$87:$B$98,D4) -> 1.15 | E7: =INDEX(Допущения!$B$87:$B$98,E4) -> 1.15 | F7: =INDEX(Допущения!$B$87:$B$98,F4) -> 1.1 | G7: =INDEX(Допущения!$B$87:$B$98,G4) -> 1 | H7: =INDEX(Допущения!$B$87:$B$98,H4) -> 1 | I7: =INDEX(Допущения!$B$87:$B$98,I4) -> 1 | J7: =INDEX(Допущения!$B$87:$B$98,J4) -> 1 | ... AM7: =INDEX(Допущения!$B$87:$B$98,AM4) -> 1
A8: Воронка
A9: Активных криейторов | C9: 0 | D9: =IF(D2<=2,Допущения!$B$22,IF(D2<=12,C9+Допущения!$E$13,MIN(Допущения!$B$24,C9+Допущения!$E$14))) -> 50 | E9: =IF(E2<=2,Допущения!$B$22,IF(E2<=12,D9+Допущения!$E$13,MIN(Допущения!$B$24,D9+Допущения!$E$14))) -> 50 | F9: =IF(F2<=2,Допущения!$B$22,IF(F2<=12,E9+Допущения!$E$13,MIN(Допущения!$B$24,E9+Допущения!$E$14))) -> 60 | G9: =IF(G2<=2,Допущения!$B$22,IF(G2<=12,F9+Допущения!$E$13,MIN(Допущения!$B$24,F9+Допущения!$E$14))) -> 70 | H9: =IF(H2<=2,Допущения!$B$22,IF(H2<=12,G9+Допущения!$E$13,MIN(Допущения!$B$24,G9+Допущения!$E$14))) -> 80 | I9: =IF(I2<=2,Допущения!$B$22,IF(I2<=12,H9+Допущения!$E$13,MIN(Допущения!$B$24,H9+Допущения!$E$14))) -> 90 | J9: =IF(J2<=2,Допущения!$B$22,IF(J2<=12,I9+Допущения!$E$13,MIN(Допущения!$B$24,I9+Допущения!$E$14))) -> 100 | K9: =IF(K2<=2,Допущения!$B$22,IF(K2<=12,J9+Допущения!$E$13,MIN(Допущения!$B$24,J9+Допущения!$E$14))) -> 110 | ... AM9: =IF(AM2<=2,Допущения!$B$22,IF(AM2<=12,AL9+Допущения!$E$13,MIN(Допущения!$B$24,AL9+Допущения!$E$14))) -> 400
A10: Роликов вышло | C10: =C9*Допущения!$B$23*Допущения!$E$8*C6 -> 0 | D10: =D9*Допущения!$B$23*Допущения!$E$8*D6 -> 146.66667 | E10: =E9*Допущения!$B$23*Допущения!$E$8*E6 -> 400 | F10: =F9*Допущения!$B$23*Допущения!$E$8*F6 -> 480 | G10: =G9*Допущения!$B$23*Допущения!$E$8*G6 -> 560 | H10: =H9*Допущения!$B$23*Допущения!$E$8*H6 -> 640 | I10: =I9*Допущения!$B$23*Допущения!$E$8*I6 -> 720 | J10: =J9*Допущения!$B$23*Допущения!$E$8*J6 -> 800 | ... AM10: =AM9*Допущения!$B$23*Допущения!$E$8*AM6 -> 3200
A11: Просмотров | C11: =C10*Допущения!$E$6 -> 0 | D11: =D10*Допущения!$E$6 -> 733333.33 | E11: =E10*Допущения!$E$6 -> 2000000 | F11: =F10*Допущения!$E$6 -> 2400000 | G11: =G10*Допущения!$E$6 -> 2800000 | H11: =H10*Допущения!$E$6 -> 3200000 | I11: =I10*Допущения!$E$6 -> 3600000 | J11: =J10*Допущения!$E$6 -> 4000000 | ... AM11: =AM10*Допущения!$E$6 -> 16000000
A12: Заказы TikTok (первые покупки) | C12: =C11*Допущения!$E$7*(1+Допущения!$E$9)*C7*(1+IF(C2>=Допущения!$B$28,Допущения!$B$27,0)*Допущения!$E$18) -> 0 | D12: =D11*Допущения!$E$7*(1+Допущения!$E$9)*D7*(1+IF(D2>=Допущения!$B$28,Допущения!$B$27,0)*Допущения!$E$18) -> 506 | E12: =E11*Допущения!$E$7*(1+Допущения!$E$9)*E7*(1+IF(E2>=Допущения!$B$28,Допущения!$B$27,0)*Допущения!$E$18) -> 1380 | F12: =F11*Допущения!$E$7*(1+Допущения!$E$9)*F7*(1+IF(F2>=Допущения!$B$28,Допущения!$B$27,0)*Допущения!$E$18) -> 1584 | G12: =G11*Допущения!$E$7*(1+Допущения!$E$9)*G7*(1+IF(G2>=Допущения!$B$28,Допущения!$B$27,0)*Допущения!$E$18) -> 2184 | H12: =H11*Допущения!$E$7*(1+Допущения!$E$9)*H7*(1+IF(H2>=Допущения!$B$28,Допущения!$B$27,0)*Допущения!$E$18) -> 2496 | I12: =I11*Допущения!$E$7*(1+Допущения!$E$9)*I7*(1+IF(I2>=Допущения!$B$28,Допущения!$B$27,0)*Допущения!$E$18) -> 2808 | J12: =J11*Допущения!$E$7*(1+Допущения!$E$9)*J7*(1+IF(J2>=Допущения!$B$28,Допущения!$B$27,0)*Допущения!$E$18) -> 3120 | ... AM12: =AM11*Допущения!$E$7*(1+Допущения!$E$9)*AM7*(1+IF(AM2>=Допущения!$B$28,Допущения!$B$27,0)*Допущения!$E$18) -> 12480
A13: Заказы Shopify прямые (первые) | C13: =C12*Допущения!$E$10 -> 0 | D13: =D12*Допущения!$E$10 -> 50.6 | E13: =E12*Допущения!$E$10 -> 138 | F13: =F12*Допущения!$E$10 -> 158.4 | G13: =G12*Допущения!$E$10 -> 218.4 | H13: =H12*Допущения!$E$10 -> 249.6 | I13: =I12*Допущения!$E$10 -> 280.8 | J13: =J12*Допущения!$E$10 -> 312 | ... AM13: =AM12*Допущения!$E$10 -> 1248
A14: Новые подписчики | C14: =(C12+C13)*Допущения!$E$11 -> 0 | D14: =(D12+D13)*Допущения!$E$11 -> 83.49 | E14: =(E12+E13)*Допущения!$E$11 -> 227.7 | F14: =(F12+F13)*Допущения!$E$11 -> 261.36 | G14: =(G12+G13)*Допущения!$E$11 -> 360.36 | H14: =(H12+H13)*Допущения!$E$11 -> 411.84 | I14: =(I12+I13)*Допущения!$E$11 -> 463.32 | J14: =(J12+J13)*Допущения!$E$11 -> 514.8 | ... AM14: =(AM12+AM13)*Допущения!$E$11 -> 2059.2
A15: Подписчиков на конец месяца | C15: 0 | D15: =C15*(1-Допущения!$E$12)+D14 -> 83.49 | E15: =D15*(1-Допущения!$E$12)+E14 -> 302.841 | F15: =E15*(1-Допущения!$E$12)+F14 -> 533.9169 | G15: =F15*(1-Допущения!$E$12)+G14 -> 840.88521 | H15: =G15*(1-Допущения!$E$12)+H14 -> 1168.6367 | I15: =H15*(1-Допущения!$E$12)+I14 -> 1515.093 | J15: =I15*(1-Допущения!$E$12)+J14 -> 1878.3837 | K15: =J15*(1-Допущения!$E$12)+K14 -> 2256.8253 | ... AM15: =AL15*(1-Допущения!$E$12)+AM14 -> 17004.955
A16: Заказы подписки (списание) | C16: 0 | D16: =C15 -> 0 | E16: =D15 -> 83.49 | F16: =E15 -> 302.841 | G16: =F15 -> 533.9169 | H16: =G15 -> 840.88521 | I16: =H15 -> 1168.6367 | J16: =I15 -> 1515.093 | K16: =J15 -> 1878.3837 | ... AM16: =AL15 -> 16606.395
A17: Amazon: продаж в день на продукт | C17: =IF(C2<Допущения!$B$35,0,IF(C2-Допущения!$B$35<=Допущения!$B$37,Допущения!$B$36+(Допущения!$E$15-Допущения!$B$36)*(C2-Допущения!$B$35)/Допущения!$B$37,Допущения!$E$15+Допущения!$E$16*(C2-Допущения!$B$35-Допущения!$B$37))) -> 0 | D17: =IF(D2<Допущения!$B$35,0,IF(D2-Допущения!$B$35<=Допущения!$B$37,Допущения!$B$36+(Допущения!$E$15-Допущения!$B$36)*(D2-Допущения!$B$35)/Допущения!$B$37,Допущения!$E$15+Допущения!$E$16*(D2-Допущения!$B$35-Допущения!$B$37))) -> 0 | E17: =IF(E2<Допущения!$B$35,0,IF(E2-Допущения!$B$35<=Допущения!$B$37,Допущения!$B$36+(Допущения!$E$15-Допущения!$B$36)*(E2-Допущения!$B$35)/Допущения!$B$37,Допущения!$E$15+Допущения!$E$16*(E2-Допущения!$B$35-Допущения!$B$37))) -> 0 | F17: =IF(F2<Допущения!$B$35,0,IF(F2-Допущения!$B$35<=Допущения!$B$37,Допущения!$B$36+(Допущения!$E$15-Допущения!$B$36)*(F2-Допущения!$B$35)/Допущения!$B$37,Допущения!$E$15+Допущения!$E$16*(F2-Допущения!$B$35-Допущения!$B$37))) -> 0 | G17: =IF(G2<Допущения!$B$35,0,IF(G2-Допущения!$B$35<=Допущения!$B$37,Допущения!$B$36+(Допущения!$E$15-Допущения!$B$36)*(G2-Допущения!$B$35)/Допущения!$B$37,Допущения!$E$15+Допущения!$E$16*(G2-Допущения!$B$35-Допущения!$B$37))) -> 0 | H17: =IF(H2<Допущения!$B$35,0,IF(H2-Допущения!$B$35<=Допущения!$B$37,Допущения!$B$36+(Допущения!$E$15-Допущения!$B$36)*(H2-Допущения!$B$35)/Допущения!$B$37,Допущения!$E$15+Допущения!$E$16*(H2-Допущения!$B$35-Допущения!$B$37))) -> 5 | I17: =IF(I2<Допущения!$B$35,0,IF(I2-Допущения!$B$35<=Допущения!$B$37,Допущения!$B$36+(Допущения!$E$15-Допущения!$B$36)*(I2-Допущения!$B$35)/Допущения!$B$37,Допущения!$E$15+Допущения!$E$16*(I2-Допущения!$B$35-Допущения!$B$37))) -> 9.1666667 | J17: =IF(J2<Допущения!$B$35,0,IF(J2-Допущения!$B$35<=Допущения!$B$37,Допущения!$B$36+(Допущения!$E$15-Допущения!$B$36)*(J2-Допущения!$B$35)/Допущения!$B$37,Допущения!$E$15+Допущения!$E$16*(J2-Допущения!$B$35-Допущения!$B$37))) -> 13.333333 | ... AM17: =IF(AM2<Допущения!$B$35,0,IF(AM2-Допущения!$B$35<=Допущения!$B$37,Допущения!$B$36+(Допущения!$E$15-Допущения!$B$36)*(AM2-Допущения!$B$35)/Допущения!$B$37,Допущения!$E$15+Допущения!$E$16*(AM2-Допущения!$B$35-Допущения!$B$37))) -> 67.5
A18: Заказы Amazon | C18: =C17*Допущения!$B$38*30.4 -> 0 | D18: =D17*Допущения!$B$38*30.4 -> 0 | E18: =E17*Допущения!$B$38*30.4 -> 0 | F18: =F17*Допущения!$B$38*30.4 -> 0 | G18: =G17*Допущения!$B$38*30.4 -> 0 | H18: =H17*Допущения!$B$38*30.4 -> 608 | I18: =I17*Допущения!$B$38*30.4 -> 1114.6667 | J18: =J17*Допущения!$B$38*30.4 -> 1621.3333 | ... AM18: =AM17*Допущения!$B$38*30.4 -> 8208
A19: Всего заказов | C19: =C12+C13+C16+C18 -> 0 | D19: =D12+D13+D16+D18 -> 556.6 | E19: =E12+E13+E16+E18 -> 1601.49 | F19: =F12+F13+F16+F18 -> 2045.241 | G19: =G12+G13+G16+G18 -> 2936.3169 | H19: =H12+H13+H16+H18 -> 4194.4852 | I19: =I12+I13+I16+I18 -> 5372.1034 | J19: =J12+J13+J16+J18 -> 6568.4264 | ... AM19: =AM12+AM13+AM16+AM18 -> 38542.395
A20: Банок продано
A21: Банок: Colostrum | C21: =(C12+C13)*Допущения!$E$74+C16*Допущения!$E$81+C18*Допущения!$F$59 -> 0 | D21: =(D12+D13)*Допущения!$E$74+D16*Допущения!$E$81+D18*Допущения!$F$59 -> 389.62 | E21: =(E12+E13)*Допущения!$E$74+E16*Допущения!$E$81+E18*Допущения!$F$59 -> 1146.09 | F21: =(F12+F13)*Допущения!$E$74+F16*Допущения!$E$81+F18*Допущения!$F$59 -> 1522.521 | G21: =(G12+G13)*Допущения!$E$74+G16*Допущения!$E$81+G18*Допущения!$F$59 -> 2215.5969 | H21: =(H12+H13)*Допущения!$E$74+H16*Допущения!$E$81+H18*Допущения!$F$59 -> 2975.6052 | I21: =(I12+I13)*Допущения!$E$74+I16*Допущения!$E$81+I18*Допущения!$F$59 -> 3720.93 | J21: =(J12+J13)*Допущения!$E$74+J16*Допущения!$E$81+J18*Допущения!$F$59 -> 4484.9597 | ... AM21: =(AM12+AM13)*Допущения!$E$74+AM16*Допущения!$E$81+AM18*Допущения!$F$59 -> 29088.795
A22: Банок: Women's Probiotic | C22: =(C12+C13)*Допущения!$F$74+C16*Допущения!$F$81+C18*Допущения!$F$60 -> 0 | D22: =(D12+D13)*Допущения!$F$74+D16*Допущения!$F$81+D18*Допущения!$F$60 -> 150.282 | E22: =(E12+E13)*Допущения!$F$74+E16*Допущения!$F$81+E18*Допущения!$F$60 -> 443.256 | F22: =(F12+F13)*Допущения!$F$74+F16*Допущения!$F$81+F18*Допущения!$F$60 -> 591.5844 | G22: =(G12+G13)*Допущения!$F$74+G16*Допущения!$F$81+G18*Допущения!$F$60 -> 862.21476 | H22: =(H12+H13)*Допущения!$F$74+H16*Допущения!$F$81+H18*Допущения!$F$60 -> 1168.8661 | I22: =(I12+I13)*Допущения!$F$74+I16*Допущения!$F$81+I18*Допущения!$F$60 -> 1468.6307 | J22: =(J12+J13)*Допущения!$F$74+J16*Допущения!$F$81+J18*Допущения!$F$60 -> 1775.8772 | ... AM22: =(AM12+AM13)*Допущения!$F$74+AM16*Допущения!$F$81+AM18*Допущения!$F$60 -> 11580.318
A23: Банок: Magnesium Glycinate | C23: =(C12+C13)*Допущения!$G$74+C16*Допущения!$G$81+C18*Допущения!$F$61 -> 0 | D23: =(D12+D13)*Допущения!$G$74+D16*Допущения!$G$81+D18*Допущения!$F$61 -> 278.3 | E23: =(E12+E13)*Допущения!$G$74+E16*Допущения!$G$81+E18*Допущения!$F$61 -> 821.6175 | F23: =(F12+F13)*Допущения!$G$74+F16*Допущения!$G$81+F18*Допущения!$F$61 -> 1098.3308 | G23: =(G12+G13)*Допущения!$G$74+G16*Допущения!$G$81+G18*Допущения!$F$61 -> 1601.6377 | H23: =(H12+H13)*Допущения!$G$74+H16*Допущения!$G$81+H18*Допущения!$F$61 -> 2155.4639 | I23: =(I12+I13)*Допущения!$G$74+I16*Допущения!$G$81+I18*Допущения!$F$61 -> 2699.5442 | J23: =(J12+J13)*Допущения!$G$74+J16*Допущения!$G$81+J18*Допущения!$F$61 -> 3257.6531 | ... AM23: =(AM12+AM13)*Допущения!$G$74+AM16*Допущения!$G$81+AM18*Допущения!$F$61 -> 21370.796
A24: Банок: Creatine | C24: =(C12+C13)*Допущения!$H$74+C16*Допущения!$H$81+C18*Допущения!$F$62 -> 0 | D24: =(D12+D13)*Допущения!$H$74+D16*Допущения!$H$81+D18*Допущения!$F$62 -> 72.358 | E24: =(E12+E13)*Допущения!$H$74+E16*Допущения!$H$81+E18*Допущения!$F$62 -> 203.60175 | F24: =(F12+F13)*Допущения!$H$74+F16*Допущения!$H$81+F18*Допущения!$F$62 -> 249.22508 | G24: =(G12+G13)*Допущения!$H$74+G16*Допущения!$H$81+G18*Допущения!$F$62 -> 352.35577 | H24: =(H12+H13)*Допущения!$H$74+H16*Допущения!$H$81+H18*Допущения!$F$62 -> 571.99439 | I24: =(I12+I13)*Допущения!$H$74+I16*Допущения!$H$81+I18*Допущения!$F$62 -> 767.85842 | J24: =(J12+J13)*Допущения!$H$74+J16*Допущения!$H$81+J18*Допущения!$F$62 -> 965.12531 | ... AM24: =(AM12+AM13)*Допущения!$H$74+AM16*Допущения!$H$81+AM18*Допущения!$F$62 -> 5082.1196
A25: Банок всего | C25: =SUM(C21:C24) -> 0 | D25: =SUM(D21:D24) -> 890.56 | E25: =SUM(E21:E24) -> 2614.5653 | F25: =SUM(F21:F24) -> 3461.6612 | G25: =SUM(G21:G24) -> 5031.8051 | H25: =SUM(H21:H24) -> 6871.9296 | I25: =SUM(I21:I24) -> 8656.9633 | J25: =SUM(J21:J24) -> 10483.615 | ... AM25: =SUM(AM21:AM24) -> 67122.028
A26: Себестоимость банки (ступень по объёму месяца)
A27: Банка: Colostrum | C27: =IFERROR(INDEX(Допущения!$H$59:$O$59,MATCH(C21,Допущения!$H$58:$O$58,1)),Допущения!$H$59)*Допущения!$E$19 -> 8.52 | D27: =IFERROR(INDEX(Допущения!$H$59:$O$59,MATCH(D21,Допущения!$H$58:$O$58,1)),Допущения!$H$59)*Допущения!$E$19 -> 8.37 | E27: =IFERROR(INDEX(Допущения!$H$59:$O$59,MATCH(E21,Допущения!$H$58:$O$58,1)),Допущения!$H$59)*Допущения!$E$19 -> 7.97 | F27: =IFERROR(INDEX(Допущения!$H$59:$O$59,MATCH(F21,Допущения!$H$58:$O$58,1)),Допущения!$H$59)*Допущения!$E$19 -> 7.97 | G27: =IFERROR(INDEX(Допущения!$H$59:$O$59,MATCH(G21,Допущения!$H$58:$O$58,1)),Допущения!$H$59)*Допущения!$E$19 -> 7.97 | H27: =IFERROR(INDEX(Допущения!$H$59:$O$59,MATCH(H21,Допущения!$H$58:$O$58,1)),Допущения!$H$59)*Допущения!$E$19 -> 7.82 | I27: =IFERROR(INDEX(Допущения!$H$59:$O$59,MATCH(I21,Допущения!$H$58:$O$58,1)),Допущения!$H$59)*Допущения!$E$19 -> 7.82 | J27: =IFERROR(INDEX(Допущения!$H$59:$O$59,MATCH(J21,Допущения!$H$58:$O$58,1)),Допущения!$H$59)*Допущения!$E$19 -> 7.82 | ... AM27: =IFERROR(INDEX(Допущения!$H$59:$O$59,MATCH(AM21,Допущения!$H$58:$O$58,1)),Допущения!$H$59)*Допущения!$E$19 -> 7.12
A28: Банка: Women's Probiotic | C28: =IFERROR(INDEX(Допущения!$H$60:$O$60,MATCH(C22,Допущения!$H$58:$O$58,1)),Допущения!$H$60)*Допущения!$E$19 -> 8.34 | D28: =IFERROR(INDEX(Допущения!$H$60:$O$60,MATCH(D22,Допущения!$H$58:$O$58,1)),Допущения!$H$60)*Допущения!$E$19 -> 8.34 | E28: =IFERROR(INDEX(Допущения!$H$60:$O$60,MATCH(E22,Допущения!$H$58:$O$58,1)),Допущения!$H$60)*Допущения!$E$19 -> 7.99 | F28: =IFERROR(INDEX(Допущения!$H$60:$O$60,MATCH(F22,Допущения!$H$58:$O$58,1)),Допущения!$H$60)*Допущения!$E$19 -> 7.64 | G28: =IFERROR(INDEX(Допущения!$H$60:$O$60,MATCH(G22,Допущения!$H$58:$O$58,1)),Допущения!$H$60)*Допущения!$E$19 -> 7.64 | H28: =IFERROR(INDEX(Допущения!$H$60:$O$60,MATCH(H22,Допущения!$H$58:$O$58,1)),Допущения!$H$60)*Допущения!$E$19 -> 7.44 | I28: =IFERROR(INDEX(Допущения!$H$60:$O$60,MATCH(I22,Допущения!$H$58:$O$58,1)),Допущения!$H$60)*Допущения!$E$19 -> 7.44 | J28: =IFERROR(INDEX(Допущения!$H$60:$O$60,MATCH(J22,Допущения!$H$58:$O$58,1)),Допущения!$H$60)*Допущения!$E$19 -> 7.44 | ... AM28: =IFERROR(INDEX(Допущения!$H$60:$O$60,MATCH(AM22,Допущения!$H$58:$O$58,1)),Допущения!$H$60)*Допущения!$E$19 -> 6.59
A29: Банка: Magnesium Glycinate | C29: =IFERROR(INDEX(Допущения!$H$61:$O$61,MATCH(C23,Допущения!$H$58:$O$58,1)),Допущения!$H$61)*Допущения!$E$19 -> 5.51 | D29: =IFERROR(INDEX(Допущения!$H$61:$O$61,MATCH(D23,Допущения!$H$58:$O$58,1)),Допущения!$H$61)*Допущения!$E$19 -> 5.51 | E29: =IFERROR(INDEX(Допущения!$H$61:$O$61,MATCH(E23,Допущения!$H$58:$O$58,1)),Допущения!$H$61)*Допущения!$E$19 -> 4.81 | F29: =IFERROR(INDEX(Допущения!$H$61:$O$61,MATCH(F23,Допущения!$H$58:$O$58,1)),Допущения!$H$61)*Допущения!$E$19 -> 4.61 | G29: =IFERROR(INDEX(Допущения!$H$61:$O$61,MATCH(G23,Допущения!$H$58:$O$58,1)),Допущения!$H$61)*Допущения!$E$19 -> 4.61 | H29: =IFERROR(INDEX(Допущения!$H$61:$O$61,MATCH(H23,Допущения!$H$58:$O$58,1)),Допущения!$H$61)*Допущения!$E$19 -> 4.61 | I29: =IFERROR(INDEX(Допущения!$H$61:$O$61,MATCH(I23,Допущения!$H$58:$O$58,1)),Допущения!$H$61)*Допущения!$E$19 -> 4.41 | J29: =IFERROR(INDEX(Допущения!$H$61:$O$61,MATCH(J23,Допущения!$H$58:$O$58,1)),Допущения!$H$61)*Допущения!$E$19 -> 4.41 | ... AM29: =IFERROR(INDEX(Допущения!$H$61:$O$61,MATCH(AM23,Допущения!$H$58:$O$58,1)),Допущения!$H$61)*Допущения!$E$19 -> 3.76
A30: Банка: Creatine | C30: =IFERROR(INDEX(Допущения!$H$62:$O$62,MATCH(C24,Допущения!$H$58:$O$58,1)),Допущения!$H$62)*Допущения!$E$19 -> 6.9 | D30: =IFERROR(INDEX(Допущения!$H$62:$O$62,MATCH(D24,Допущения!$H$58:$O$58,1)),Допущения!$H$62)*Допущения!$E$19 -> 6.9 | E30: =IFERROR(INDEX(Допущения!$H$62:$O$62,MATCH(E24,Допущения!$H$58:$O$58,1)),Допущения!$H$62)*Допущения!$E$19 -> 6.9 | F30: =IFERROR(INDEX(Допущения!$H$62:$O$62,MATCH(F24,Допущения!$H$58:$O$58,1)),Допущения!$H$62)*Допущения!$E$19 -> 6.9 | G30: =IFERROR(INDEX(Допущения!$H$62:$O$62,MATCH(G24,Допущения!$H$58:$O$58,1)),Допущения!$H$62)*Допущения!$E$19 -> 6.75 | H30: =IFERROR(INDEX(Допущения!$H$62:$O$62,MATCH(H24,Допущения!$H$58:$O$58,1)),Допущения!$H$62)*Допущения!$E$19 -> 6.5 | I30: =IFERROR(INDEX(Допущения!$H$62:$O$62,MATCH(I24,Допущения!$H$58:$O$58,1)),Допущения!$H$62)*Допущения!$E$19 -> 6.5 | J30: =IFERROR(INDEX(Допущения!$H$62:$O$62,MATCH(J24,Допущения!$H$58:$O$58,1)),Допущения!$H$62)*Допущения!$E$19 -> 6.5 | ... AM30: =IFERROR(INDEX(Допущения!$H$62:$O$62,MATCH(AM24,Допущения!$H$58:$O$58,1)),Допущения!$H$62)*Допущения!$E$19 -> 6.05
A31: Выручка
A32: TikTok Shop | C32: =C12*Допущения!$B$74 -> 0 | D32: =D12*Допущения!$B$74 -> 25704.8 | E32: =E12*Допущения!$B$74 -> 70104 | F32: =F12*Допущения!$B$74 -> 80467.2 | G32: =G12*Допущения!$B$74 -> 110947.2 | H32: =H12*Допущения!$B$74 -> 126796.8 | I32: =I12*Допущения!$B$74 -> 142646.4 | J32: =J12*Допущения!$B$74 -> 158496 | ... AM32: =AM12*Допущения!$B$74 -> 633984
A33: Shopify: первые покупки | C33: =C13*Допущения!$B$74 -> 0 | D33: =D13*Допущения!$B$74 -> 2570.48 | E33: =E13*Допущения!$B$74 -> 7010.4 | F33: =F13*Допущения!$B$74 -> 8046.72 | G33: =G13*Допущения!$B$74 -> 11094.72 | H33: =H13*Допущения!$B$74 -> 12679.68 | I33: =I13*Допущения!$B$74 -> 14264.64 | J33: =J13*Допущения!$B$74 -> 15849.6 | ... AM33: =AM13*Допущения!$B$74 -> 63398.4
A34: Shopify: подписка | C34: =C16*Допущения!$B$81 -> 0 | D34: =D16*Допущения!$B$81 -> 0 | E34: =E16*Допущения!$B$81 -> 5255.6955 | F34: =F16*Допущения!$B$81 -> 19063.841 | G34: =G16*Допущения!$B$81 -> 33610.069 | H34: =H16*Допущения!$B$81 -> 52933.724 | I34: =I16*Допущения!$B$81 -> 73565.68 | J34: =J16*Допущения!$B$81 -> 95375.106 | ... AM34: =AM16*Допущения!$B$81 -> 1045372.5
A35: Amazon | C35: =C18*Допущения!$B$83 -> 0 | D35: =D18*Допущения!$B$83 -> 0 | E35: =E18*Допущения!$B$83 -> 0 | F35: =F18*Допущения!$B$83 -> 0 | G35: =G18*Допущения!$B$83 -> 0 | H35: =H18*Допущения!$B$83 -> 20793.6 | I35: =I18*Допущения!$B$83 -> 38121.6 | J35: =J18*Допущения!$B$83 -> 55449.6 | ... AM35: =AM18*Допущения!$B$83 -> 280713.6
A36: Выручка всего | C36: =SUM(C32:C35) -> 0 | D36: =SUM(D32:D35) -> 28275.28 | E36: =SUM(E32:E35) -> 82370.095 | F36: =SUM(F32:F35) -> 107577.76 | G36: =SUM(G32:G35) -> 155651.99 | H36: =SUM(H32:H35) -> 213203.8 | I36: =SUM(I32:I35) -> 268598.32 | J36: =SUM(J32:J35) -> 325170.31 | ... AM36: =SUM(AM32:AM35) -> 2023468.5
A37: Переменные расходы
A38: Товар (Vox) | C38: =C21*C27+C22*C28+C23*C29+C24*C30 -> 0 | D38: =D21*D27+D22*D28+D23*D29+D24*D30 -> 6547.1745 | E38: =E21*E27+E22*E28+E23*E29+E24*E30 -> 18032.785 | F38: =F21*F27+F22*F28+F23*F29+F24*F30 -> 23437.155 | G38: =G21*G27+G22*G28+G23*G29+G24*G30 -> 34007.579 | H38: =H21*H27+H22*H28+H23*H29+H24*H30 -> 45620.249 | I38: =I21*I27+I22*I28+I23*I29+I24*I30 -> 56920.355 | J38: =J21*J27+J22*J28+J23*J29+J24*J30 -> 68924.476 | ... AM38: =AM21*AM27+AM22*AM28+AM23*AM29+AM24*AM30 -> 394527.53
A39: Комиссия TikTok Shop | C39: =Допущения!$B$26*C32 -> 0 | D39: =Допущения!$B$26*D32 -> 2056.384 | E39: =Допущения!$B$26*E32 -> 5608.32 | F39: =Допущения!$B$26*F32 -> 6437.376 | G39: =Допущения!$B$26*G32 -> 8875.776 | H39: =Допущения!$B$26*H32 -> 10143.744 | I39: =Допущения!$B$26*I32 -> 11411.712 | J39: =Допущения!$B$26*J32 -> 12679.68 | ... AM39: =Допущения!$B$26*AM32 -> 50718.72
A40: Комиссия криейторов | C40: =Допущения!$B$29*C32 -> 0 | D40: =Допущения!$B$29*D32 -> 7711.44 | E40: =Допущения!$B$29*E32 -> 21031.2 | F40: =Допущения!$B$29*F32 -> 24140.16 | G40: =Допущения!$B$29*G32 -> 33284.16 | H40: =Допущения!$B$29*H32 -> 38039.04 | I40: =Допущения!$B$29*I32 -> 42793.92 | J40: =Допущения!$B$29*J32 -> 47548.8 | ... AM40: =Допущения!$B$29*AM32 -> 190195.2
A41: Эквайринг Shopify | C41: =Допущения!$B$31*(C33+C34)+Допущения!$B$32*(C13+C16) -> 0 | D41: =Допущения!$B$31*(D33+D34)+Допущения!$B$32*(D13+D16) -> 89.72392 | E41: =Допущения!$B$31*(E33+E34)+Допущения!$B$32*(E13+E16) -> 422.16377 | F41: =Допущения!$B$31*(F33+F34)+Допущения!$B$32*(F13+F16) -> 924.57857 | G41: =Допущения!$B$31*(G33+G34)+Допущения!$B$32*(G13+G16) -> 1522.1339 | H41: =Допущения!$B$31*(H33+H34)+Допущения!$B$32*(H13+H16) -> 2229.9343 | I41: =Допущения!$B$31*(I33+I34)+Допущения!$B$32*(I13+I16) -> 2981.9103 | J41: =Допущения!$B$31*(J33+J34)+Допущения!$B$32*(J13+J16) -> 3773.6444 | ... AM41: =Допущения!$B$31*(AM33+AM34)+Допущения!$B$32*(AM13+AM16) -> 37510.676
A42: Amazon: комиссия и FBA | C42: =Допущения!$B$34*C35+C18*Допущения!$B$84 -> 0 | D42: =Допущения!$B$34*D35+D18*Допущения!$B$84 -> 0 | E42: =Допущения!$B$34*E35+E18*Допущения!$B$84 -> 0 | F42: =Допущения!$B$34*F35+F18*Допущения!$B$84 -> 0 | G42: =Допущения!$B$34*G35+G18*Допущения!$B$84 -> 0 | H42: =Допущения!$B$34*H35+H18*Допущения!$B$84 -> 6821.76 | I42: =Допущения!$B$34*I35+I18*Допущения!$B$84 -> 12506.56 | J42: =Допущения!$B$34*J35+J18*Допущения!$B$84 -> 18191.36 | ... AM42: =Допущения!$B$34*AM35+AM18*Допущения!$B$84 -> 92093.76
A43: Amazon: реклама PPC | C43: =Допущения!$E$17*C35 -> 0 | D43: =Допущения!$E$17*D35 -> 0 | E43: =Допущения!$E$17*E35 -> 0 | F43: =Допущения!$E$17*F35 -> 0 | G43: =Допущения!$E$17*G35 -> 0 | H43: =Допущения!$E$17*H35 -> 3119.04 | I43: =Допущения!$E$17*I35 -> 5718.24 | J43: =Допущения!$E$17*J35 -> 8317.44 | ... AM43: =Допущения!$E$17*AM35 -> 42107.04
A44: Доставка покупателю | C44: =(C12+C13)*Допущения!$C$74+C16*Допущения!$C$81 -> 0 | D44: =(D12+D13)*Допущения!$C$74+D16*Допущения!$C$81 -> 2788.566 | E44: =(E12+E13)*Допущения!$C$74+E16*Допущения!$C$81 -> 8089.422 | F44: =(F12+F13)*Допущения!$C$74+F16*Допущения!$C$81 -> 10485.902 | G44: =(G12+G13)*Допущения!$C$74+G16*Допущения!$C$81 -> 15132.742 | H44: =(H12+H13)*Допущения!$C$74+H16*Допущения!$C$81 -> 18632.59 | I44: =(I12+I13)*Допущения!$C$74+I16*Допущения!$C$81 -> 22252.981 | J44: =(J12+J13)*Допущения!$C$74+J16*Допущения!$C$81 -> 25981.86 | ... AM44: =(AM12+AM13)*Допущения!$C$74+AM16*Допущения!$C$81 -> 165094.37
A45: Склад-отправщик | C45: =Допущения!$B$39*(C12+C13+C16) -> 0 | D45: =Допущения!$B$39*(D12+D13+D16) -> 1391.5 | E45: =Допущения!$B$39*(E12+E13+E16) -> 4003.725 | F45: =Допущения!$B$39*(F12+F13+F16) -> 5113.1025 | G45: =Допущения!$B$39*(G12+G13+G16) -> 7340.7923 | H45: =Допущения!$B$39*(H12+H13+H16) -> 8966.213 | I45: =Допущения!$B$39*(I12+I13+I16) -> 10643.592 | J45: =Допущения!$B$39*(J12+J13+J16) -> 12367.733 | ... AM45: =Допущения!$B$39*(AM12+AM13+AM16) -> 75835.987
A46: Возвраты | C46: =Допущения!$B$30*C32+Допущения!$B$33*(C33+C34) -> 0 | D46: =Допущения!$B$30*D32+Допущения!$B$33*(D33+D34) -> 822.5536 | E46: =Допущения!$B$30*E32+Допущения!$B$33*(E33+E34) -> 2348.4419 | F46: =Допущения!$B$30*F32+Допущения!$B$33*(F33+F34) -> 2956.2272 | G46: =Допущения!$B$30*G32+Допущения!$B$33*(G33+G34) -> 4222.5118 | H46: =Допущения!$B$30*H32+Допущения!$B$33*(H33+H34) -> 5116.1721 | I46: =Допущения!$B$30*I32+Допущения!$B$33*(I33+I34) -> 6035.9984 | J46: =Допущения!$B$30*J32+Допущения!$B$33*(J33+J34) -> 6979.3741 | ... AM46: =Допущения!$B$30*AM32+Допущения!$B$33*(AM33+AM34) -> 41194.939
A47: Переменные расходы всего | C47: =SUM(C38:C46) -> 0 | D47: =SUM(D38:D46) -> 21407.342 | E47: =SUM(E38:E46) -> 59536.058 | F47: =SUM(F38:F46) -> 73494.501 | G47: =SUM(G38:G46) -> 104385.7 | H47: =SUM(H38:H46) -> 138688.74 | I47: =SUM(I38:I46) -> 171265.27 | J47: =SUM(J38:J46) -> 204764.37 | ... AM47: =SUM(AM38:AM46) -> 1089278.2
A48: Маржинальная прибыль | C48: =C36-C47 -> 0 | D48: =D36-D47 -> 6867.938 | E48: =E36-E47 -> 22834.038 | F48: =F36-F47 -> 34083.26 | G48: =G36-G47 -> 51266.294 | H48: =H36-H47 -> 74515.062 | I48: =I36-I47 -> 97333.052 | J48: =J36-J47 -> 120405.94 | ... AM48: =AM36-AM47 -> 934190.33
A49: Маржинальность | C49: =IF(C36=0,0,C48/C36) -> 0 | D49: =IF(D36=0,0,D48/D36) -> 0.24289549 | E49: =IF(E36=0,0,E48/E36) -> 0.27721272 | F49: =IF(F36=0,0,F48/F36) -> 0.3168244 | G49: =IF(G36=0,0,G48/G36) -> 0.32936485 | H49: =IF(H36=0,0,H48/H36) -> 0.34950156 | I49: =IF(I36=0,0,I48/I36) -> 0.36237402 | J49: =IF(J36=0,0,J48/J36) -> 0.37028578 | ... AM49: =IF(AM36=0,0,AM48/AM36) -> 0.46167771
A50: Постоянные расходы
A51: Сервисы и ПО | C51: =IF(C5=0,0,CHOOSE(C5,Допущения!$B$43,Допущения!$B$44,Допущения!$B$45)) -> 0 | D51: =IF(D5=0,0,CHOOSE(D5,Допущения!$B$43,Допущения!$B$44,Допущения!$B$45)) -> 500 | E51: =IF(E5=0,0,CHOOSE(E5,Допущения!$B$43,Допущения!$B$44,Допущения!$B$45)) -> 500 | F51: =IF(F5=0,0,CHOOSE(F5,Допущения!$B$43,Допущения!$B$44,Допущения!$B$45)) -> 500 | G51: =IF(G5=0,0,CHOOSE(G5,Допущения!$B$43,Допущения!$B$44,Допущения!$B$45)) -> 500 | H51: =IF(H5=0,0,CHOOSE(H5,Допущения!$B$43,Допущения!$B$44,Допущения!$B$45)) -> 500 | I51: =IF(I5=0,0,CHOOSE(I5,Допущения!$B$43,Допущения!$B$44,Допущения!$B$45)) -> 500 | J51: =IF(J5=0,0,CHOOSE(J5,Допущения!$B$43,Допущения!$B$44,Допущения!$B$45)) -> 500 | ... AM51: =IF(AM5=0,0,CHOOSE(AM5,Допущения!$B$43,Допущения!$B$44,Допущения!$B$45)) -> 1500
A52: Страховка | C52: =IF(C2=0,0,IF(C2<12,Допущения!$B$46,Допущения!$B$47)) -> 0 | D52: =IF(D2=0,0,IF(D2<12,Допущения!$B$46,Допущения!$B$47)) -> 150 | E52: =IF(E2=0,0,IF(E2<12,Допущения!$B$46,Допущения!$B$47)) -> 150 | F52: =IF(F2=0,0,IF(F2<12,Допущения!$B$46,Допущения!$B$47)) -> 150 | G52: =IF(G2=0,0,IF(G2<12,Допущения!$B$46,Допущения!$B$47)) -> 150 | H52: =IF(H2=0,0,IF(H2<12,Допущения!$B$46,Допущения!$B$47)) -> 150 | I52: =IF(I2=0,0,IF(I2<12,Допущения!$B$46,Допущения!$B$47)) -> 150 | J52: =IF(J2=0,0,IF(J2<12,Допущения!$B$46,Допущения!$B$47)) -> 150 | ... AM52: =IF(AM2=0,0,IF(AM2<12,Допущения!$B$46,Допущения!$B$47)) -> 500
A53: Бухгалтерия и юристы | C53: =IF(C2=0,0,Допущения!$B$48) -> 0 | D53: =IF(D2=0,0,Допущения!$B$48) -> 300 | E53: =IF(E2=0,0,Допущения!$B$48) -> 300 | F53: =IF(F2=0,0,Допущения!$B$48) -> 300 | G53: =IF(G2=0,0,Допущения!$B$48) -> 300 | H53: =IF(H2=0,0,Допущения!$B$48) -> 300 | I53: =IF(I2=0,0,Допущения!$B$48) -> 300 | J53: =IF(J2=0,0,Допущения!$B$48) -> 300 | ... AM53: =IF(AM2=0,0,Допущения!$B$48) -> 300
A54: Команда | C54: =IF(C2=0,0,SUMPRODUCT((Допущения!$C$102:$C$107<=C2)*Допущения!$B$102:$B$107)) -> 0 | D54: =IF(D2=0,0,SUMPRODUCT((Допущения!$C$102:$C$107<=D2)*Допущения!$B$102:$B$107)) -> 0 | E54: =IF(E2=0,0,SUMPRODUCT((Допущения!$C$102:$C$107<=E2)*Допущения!$B$102:$B$107)) -> 0 | F54: =IF(F2=0,0,SUMPRODUCT((Допущения!$C$102:$C$107<=F2)*Допущения!$B$102:$B$107)) -> 0 | G54: =IF(G2=0,0,SUMPRODUCT((Допущения!$C$102:$C$107<=G2)*Допущения!$B$102:$B$107)) -> 0 | H54: =IF(H2=0,0,SUMPRODUCT((Допущения!$C$102:$C$107<=H2)*Допущения!$B$102:$B$107)) -> 4000 | I54: =IF(I2=0,0,SUMPRODUCT((Допущения!$C$102:$C$107<=I2)*Допущения!$B$102:$B$107)) -> 7000 | J54: =IF(J2=0,0,SUMPRODUCT((Допущения!$C$102:$C$107<=J2)*Допущения!$B$102:$B$107)) -> 7000 | ... AM54: =IF(AM2=0,0,SUMPRODUCT((Допущения!$C$102:$C$107<=AM2)*Допущения!$B$102:$B$107)) -> 21000
A55: Реклама: Spark Ads на выстрелившие ролики и прочая | C55: =IF(C2>=Допущения!$B$28,Допущения!$B$27,0)*C32/(1+IF(C2>=Допущения!$B$28,Допущения!$B$27,0)*Допущения!$E$18)+Допущения!$B$49*C36 -> 0 | D55: =IF(D2>=Допущения!$B$28,Допущения!$B$27,0)*D32/(1+IF(D2>=Допущения!$B$28,Допущения!$B$27,0)*Допущения!$E$18)+Допущения!$B$49*D36 -> 0 | E55: =IF(E2>=Допущения!$B$28,Допущения!$B$27,0)*E32/(1+IF(E2>=Допущения!$B$28,Допущения!$B$27,0)*Допущения!$E$18)+Допущения!$B$49*E36 -> 0 | F55: =IF(F2>=Допущения!$B$28,Допущения!$B$27,0)*F32/(1+IF(F2>=Допущения!$B$28,Допущения!$B$27,0)*Допущения!$E$18)+Допущения!$B$49*F36 -> 0 | G55: =IF(G2>=Допущения!$B$28,Допущения!$B$27,0)*G32/(1+IF(G2>=Допущения!$B$28,Допущения!$B$27,0)*Допущения!$E$18)+Допущения!$B$49*G36 -> 8534.4 | H55: =IF(H2>=Допущения!$B$28,Допущения!$B$27,0)*H32/(1+IF(H2>=Допущения!$B$28,Допущения!$B$27,0)*Допущения!$E$18)+Допущения!$B$49*H36 -> 9753.6 | I55: =IF(I2>=Допущения!$B$28,Допущения!$B$27,0)*I32/(1+IF(I2>=Допущения!$B$28,Допущения!$B$27,0)*Допущения!$E$18)+Допущения!$B$49*I36 -> 10972.8 | J55: =IF(J2>=Допущения!$B$28,Допущения!$B$27,0)*J32/(1+IF(J2>=Допущения!$B$28,Допущения!$B$27,0)*Допущения!$E$18)+Допущения!$B$49*J36 -> 12192 | ... AM55: =IF(AM2>=Допущения!$B$28,Допущения!$B$27,0)*AM32/(1+IF(AM2>=Допущения!$B$28,Допущения!$B$27,0)*Допущения!$E$18)+Допущения!$B$49*AM36 -> 48768
A56: Постоянные расходы всего | C56: =SUM(C51:C55) -> 0 | D56: =SUM(D51:D55) -> 950 | E56: =SUM(E51:E55) -> 950 | F56: =SUM(F51:F55) -> 950 | G56: =SUM(G51:G55) -> 9484.4 | H56: =SUM(H51:H55) -> 14703.6 | I56: =SUM(I51:I55) -> 18922.8 | J56: =SUM(J51:J55) -> 20142 | ... AM56: =SUM(AM51:AM55) -> 72068
A57: EBITDA (прибыль до налога) | C57: =C48-C56 -> 0 | D57: =D48-D56 -> 5917.938 | E57: =E48-E56 -> 21884.038 | F57: =F48-F56 -> 33133.26 | G57: =G48-G56 -> 41781.894 | H57: =H48-H56 -> 59811.462 | I57: =I48-I56 -> 78410.252 | J57: =J48-J56 -> 100263.94 | ... AM57: =AM48-AM56 -> 862122.33
A58: Налог на прибыль, оценка | C58: =MAX(0,C57)*Допущения!$B$50 -> 0 | D58: =MAX(0,D57)*Допущения!$B$50 -> 1479.4845 | E58: =MAX(0,E57)*Допущения!$B$50 -> 5471.0095 | F58: =MAX(0,F57)*Допущения!$B$50 -> 8283.315 | G58: =MAX(0,G57)*Допущения!$B$50 -> 10445.473 | H58: =MAX(0,H57)*Допущения!$B$50 -> 14952.865 | I58: =MAX(0,I57)*Допущения!$B$50 -> 19602.563 | J58: =MAX(0,J57)*Допущения!$B$50 -> 25065.985 | ... AM58: =MAX(0,AM57)*Допущения!$B$50 -> 215530.58
A59: Чистая прибыль | C59: =C57-C58 -> 0 | D59: =D57-D58 -> 4438.4535 | E59: =E57-E58 -> 16413.028 | F59: =F57-F58 -> 24849.945 | G59: =G57-G58 -> 31336.42 | H59: =H57-H58 -> 44858.596 | I59: =I57-I58 -> 58807.689 | J59: =J57-J58 -> 75197.954 | ... AM59: =AM57-AM58 -> 646591.75
A60: Запуск и знак (месяц 0) | C60: =IF(C2=0,Допущения!$B$53+Допущения!$B$54,0) -> 2599 | D60: =IF(D2=0,Допущения!$B$53+Допущения!$B$54,0) -> 0 | E60: =IF(E2=0,Допущения!$B$53+Допущения!$B$54,0) -> 0 | F60: =IF(F2=0,Допущения!$B$53+Допущения!$B$54,0) -> 0 | G60: =IF(G2=0,Допущения!$B$53+Допущения!$B$54,0) -> 0 | H60: =IF(H2=0,Допущения!$B$53+Допущения!$B$54,0) -> 0 | I60: =IF(I2=0,Допущения!$B$53+Допущения!$B$54,0) -> 0 | J60: =IF(J2=0,Допущения!$B$53+Допущения!$B$54,0) -> 0 | ... AM60: =IF(AM2=0,Допущения!$B$53+Допущения!$B$54,0) -> 0
A61: Денежный поток
A62: Поступления TikTok | C62: 0 | D62: =(D32-D39-D40-Допущения!$B$30*D32)*(1-Допущения!$B$40)+(C32-C39-C40-Допущения!$B$30*C32)*Допущения!$B$40 -> 7582.916 | E62: =(E32-E39-E40-Допущения!$B$30*E32)*(1-Допущения!$B$40)+(D32-D39-D40-Допущения!$B$30*D32)*Допущения!$B$40 -> 28263.596 | F62: =(F32-F39-F40-Допущения!$B$30*F32)*(1-Допущения!$B$40)+(E32-E39-E40-Допущения!$B$30*E32)*Допущения!$B$40 -> 44418.504 | G62: =(G32-G39-G40-Допущения!$B$30*G32)*(1-Допущения!$B$40)+(F32-F39-F40-Допущения!$B$30*F32)*Допущения!$B$40 -> 56467.248 | H62: =(H32-H39-H40-Допущения!$B$30*H32)*(1-Допущения!$B$40)+(G32-G39-G40-Допущения!$B$30*G32)*Допущения!$B$40 -> 70134.48 | I62: =(I32-I39-I40-Допущения!$B$30*I32)*(1-Допущения!$B$40)+(H32-H39-H40-Допущения!$B$30*H32)*Допущения!$B$40 -> 79485.744 | J62: =(J32-J39-J40-Допущения!$B$30*J32)*(1-Допущения!$B$40)+(I32-I39-I40-Допущения!$B$30*I32)*Допущения!$B$40 -> 88837.008 | K62: =(K32-K39-K40-Допущения!$B$30*K32)*(1-Допущения!$B$40)+(J32-J39-J40-Допущения!$B$30*J32)*Допущения!$B$40 -> 98188.272 | ... AM62: =(AM32-AM39-AM40-Допущения!$B$30*AM32)*(1-Допущения!$B$40)+(AL32-AL39-AL40-Допущения!$B$30*AL32)*Допущения!$B$40 -> 374050.56
A63: Поступления Shopify | C63: =C33+C34-C41-Допущения!$B$33*(C33+C34) -> 0 | D63: =D33+D34-D41-Допущения!$B$33*(D33+D34) -> 2429.3465 | E63: =E33+E34-E41-Допущения!$B$33*(E33+E34) -> 11598.61 | F63: =F33+F34-F41-Допущения!$B$33*(F33+F34) -> 25643.771 | G63: =G33+G34-G41-Допущения!$B$33*(G33+G34) -> 42288.559 | H63: =H33+H34-H41-Допущения!$B$33*(H33+H34) -> 62071.202 | I63: =I33+I34-I41-Допущения!$B$33*(I33+I34) -> 83091.803 | J63: =J33+J34-J41-Допущения!$B$33*(J33+J34) -> 105226.57 | ... AM63: =AM33+AM34-AM41-Допущения!$B$33*(AM33+AM34) -> 1049084.9
A64: Поступления Amazon | C64: 0 | D64: =(D35-D42-D43)*(1-Допущения!$B$40)+(C35-C42-C43)*Допущения!$B$40 -> 0 | E64: =(E35-E42-E43)*(1-Допущения!$B$40)+(D35-D42-D43)*Допущения!$B$40 -> 0 | F64: =(F35-F42-F43)*(1-Допущения!$B$40)+(E35-E42-E43)*Допущения!$B$40 -> 0 | G64: =(G35-G42-G43)*(1-Допущения!$B$40)+(F35-F42-F43)*Допущения!$B$40 -> 0 | H64: =(H35-H42-H43)*(1-Допущения!$B$40)+(G35-G42-G43)*Допущения!$B$40 -> 5426.4 | I64: =(I35-I42-I43)*(1-Допущения!$B$40)+(H35-H42-H43)*Допущения!$B$40 -> 15374.8 | J64: =(J35-J42-J43)*(1-Допущения!$B$40)+(I35-I42-I43)*Допущения!$B$40 -> 24418.8 | K64: =(K35-K42-K43)*(1-Допущения!$B$40)+(J35-J42-J43)*Допущения!$B$40 -> 33462.8 | ... AM64: =(AM35-AM42-AM43)*(1-Допущения!$B$40)+(AL35-AL42-AL43)*Допущения!$B$40 -> 144884.88
A65: Поступления всего | C65: =SUM(C62:C64) -> 0 | D65: =SUM(D62:D64) -> 10012.262 | E65: =SUM(E62:E64) -> 39862.206 | F65: =SUM(F62:F64) -> 70062.275 | G65: =SUM(G62:G64) -> 98755.807 | H65: =SUM(H62:H64) -> 137632.08 | I65: =SUM(I62:I64) -> 177952.35 | J65: =SUM(J62:J64) -> 218482.38 | ... AM65: =SUM(AM62:AM64) -> 1568020.3
A66: Доставка и склад | C66: =C44+C45 -> 0 | D66: =D44+D45 -> 4180.066 | E66: =E44+E45 -> 12093.147 | F66: =F44+F45 -> 15599.004 | G66: =G44+G45 -> 22473.534 | H66: =H44+H45 -> 27598.803 | I66: =I44+I45 -> 32896.573 | J66: =J44+J45 -> 38349.592 | ... AM66: =AM44+AM45 -> 240930.36
A67: Постоянные расходы | C67: =C56 -> 0 | D67: =D56 -> 950 | E67: =E56 -> 950 | F67: =F56 -> 950 | G67: =G56 -> 9484.4 | H67: =H56 -> 14703.6 | I67: =I56 -> 18922.8 | J67: =J56 -> 20142 | ... AM67: =AM56 -> 72068
A68: Налог | C68: =C58 -> 0 | D68: =D58 -> 1479.4845 | E68: =E58 -> 5471.0095 | F68: =F58 -> 8283.315 | G68: =G58 -> 10445.473 | H68: =H58 -> 14952.865 | I68: =I58 -> 19602.563 | J68: =J58 -> 25065.985 | ... AM68: =AM58 -> 215530.58
A69: Закупка товара у Vox | C69: =C77+C81+C85+C89 -> 17156 | D69: =D77+D81+D85+D89 -> 12945.5 | E69: =E77+E81+E85+E89 -> 25373.5 | F69: =F77+F81+F85+F89 -> 37153.5 | G69: =G77+G81+G85+G89 -> 49382.5 | H69: =H77+H81+H85+H89 -> 60189.5 | I69: =I77+I81+I85+I89 -> 72570.5 | J69: =J77+J81+J85+J89 -> 83813 | ... AM69: =AM77+AM81+AM85+AM89 -> 394464.5
A70: Запуск и знак | C70: =C60 -> 2599 | D70: =D60 -> 0 | E70: =E60 -> 0 | F70: =F60 -> 0 | G70: =G60 -> 0 | H70: =H60 -> 0 | I70: =I60 -> 0 | J70: =J60 -> 0 | ... AM70: =AM60 -> 0
A71: Вложения владельца | C71: =IF(C2=0,Допущения!$B$51,IF(C2=1,Допущения!$B$52,0)) -> 20000 | D71: =IF(D2=0,Допущения!$B$51,IF(D2=1,Допущения!$B$52,0)) -> 5000 | E71: =IF(E2=0,Допущения!$B$51,IF(E2=1,Допущения!$B$52,0)) -> 0 | F71: =IF(F2=0,Допущения!$B$51,IF(F2=1,Допущения!$B$52,0)) -> 0 | G71: =IF(G2=0,Допущения!$B$51,IF(G2=1,Допущения!$B$52,0)) -> 0 | H71: =IF(H2=0,Допущения!$B$51,IF(H2=1,Допущения!$B$52,0)) -> 0 | I71: =IF(I2=0,Допущения!$B$51,IF(I2=1,Допущения!$B$52,0)) -> 0 | J71: =IF(J2=0,Допущения!$B$51,IF(J2=1,Допущения!$B$52,0)) -> 0 | ... AM71: =IF(AM2=0,Допущения!$B$51,IF(AM2=1,Допущения!$B$52,0)) -> 0
A72: Чистый денежный поток | C72: =C65-C66-C67-C68-C69-C70+C71 -> 245 | D72: =D65-D66-D67-D68-D69-D70+D71 -> -4542.788 | E72: =E65-E66-E67-E68-E69-E70+E71 -> -4025.4506 | F72: =F65-F66-F67-F68-F69-F70+F71 -> 8076.4559 | G72: =G65-G66-G67-G68-G69-G70+G71 -> 6969.8994 | H72: =H65-H66-H67-H68-H69-H70+H71 -> 20187.313 | I72: =I65-I66-I67-I68-I69-I70+I71 -> 33959.911 | J72: =J65-J66-J67-J68-J69-J70+J71 -> 51111.798 | ... AM72: =AM65-AM66-AM67-AM68-AM69-AM70+AM71 -> 645026.86
A73: Деньги на счёте на конец месяца | C73: =C72 -> 245 | D73: =C73+D72 -> -4297.788 | E73: =D73+E72 -> -8323.2387 | F73: =E73+F72 -> -246.78277 | G73: =F73+G72 -> 6723.1167 | H73: =G73+H72 -> 26910.43 | I73: =H73+I72 -> 60870.341 | J73: =I73+J72 -> 111982.14 | K73: =J73+K72 -> 179854.39 | ... AM73: =AL73+AM72 -> 10138854
A74: Склад и перезаказы (заказ в месяце приходит к следующему)
A75: Colostrum: остаток на начало | C75: 0 | D75: =C78 -> 1000 | E75: =D78 -> 1510.38 | F75: =E78 -> 2014.29 | G75: =F78 -> 2891.769 | H75: =G78 -> 3876.1721 | I75: =H78 -> 4850.5669 | J75: =I78 -> 5879.6369 | K75: =J78 -> 6894.6772 | ... AM75: =AL78 -> 37853.325
A76: Colostrum: перезаказ, банок | C76: =Допущения!$G$59 -> 1000 | D76: =IF(Допущения!$B$41*E21>D75-D21,MAX(Допущения!$B$42,CEILING(Допущения!$B$41*E21-(D75-D21),50)),0) -> 900 | E76: =IF(Допущения!$B$41*F21>E75-E21,MAX(Допущения!$B$42,CEILING(Допущения!$B$41*F21-(E75-E21),50)),0) -> 1650 | F76: =IF(Допущения!$B$41*G21>F75-F21,MAX(Допущения!$B$42,CEILING(Допущения!$B$41*G21-(F75-F21),50)),0) -> 2400 | G76: =IF(Допущения!$B$41*H21>G75-G21,MAX(Допущения!$B$42,CEILING(Допущения!$B$41*H21-(G75-G21),50)),0) -> 3200 | H76: =IF(Допущения!$B$41*I21>H75-H21,MAX(Допущения!$B$42,CEILING(Допущения!$B$41*I21-(H75-H21),50)),0) -> 3950 | I76: =IF(Допущения!$B$41*J21>I75-I21,MAX(Допущения!$B$42,CEILING(Допущения!$B$41*J21-(I75-I21),50)),0) -> 4750 | J76: =IF(Допущения!$B$41*K21>J75-J21,MAX(Допущения!$B$42,CEILING(Допущения!$B$41*K21-(J75-J21),50)),0) -> 5500 | K76: =IF(Допущения!$B$41*L21>K75-K21,MAX(Допущения!$B$42,CEILING(Допущения!$B$41*L21-(K75-K21),50)),0) -> 6300 | ... AL76: =IF(Допущения!$B$41*AM21>AL75-AL21,MAX(Допущения!$B$42,CEILING(Допущения!$B$41*AM21-(AL75-AL21),50)),0) -> 29250 | AM76: =IF(Допущения!$B$41*AM21>AM75-AM21,MAX(Допущения!$B$42,CEILING(Допущения!$B$41*AM21-(AM75-AM21),50)),0) -> 29100
A77: Colostrum: перезаказ, $ | C77: =IF(C76=0,0,C76*IFERROR(INDEX(Допущения!$H$59:$O$59,MATCH(C76,Допущения!$H$58:$O$58,1)),Допущения!$H$59)*IF(C2=0,1,Допущения!$E$19)) -> 7970 | D77: =IF(D76=0,0,D76*IFERROR(INDEX(Допущения!$H$59:$O$59,MATCH(D76,Допущения!$H$58:$O$58,1)),Допущения!$H$59)*IF(D2=0,1,Допущения!$E$19)) -> 7308 | E77: =IF(E76=0,0,E76*IFERROR(INDEX(Допущения!$H$59:$O$59,MATCH(E76,Допущения!$H$58:$O$58,1)),Допущения!$H$59)*IF(E2=0,1,Допущения!$E$19)) -> 13150.5 | F77: =IF(F76=0,0,F76*IFERROR(INDEX(Допущения!$H$59:$O$59,MATCH(F76,Допущения!$H$58:$O$58,1)),Допущения!$H$59)*IF(F2=0,1,Допущения!$E$19)) -> 19128 | G77: =IF(G76=0,0,G76*IFERROR(INDEX(Допущения!$H$59:$O$59,MATCH(G76,Допущения!$H$58:$O$58,1)),Допущения!$H$59)*IF(G2=0,1,Допущения!$E$19)) -> 25024 | H77: =IF(H76=0,0,H76*IFERROR(INDEX(Допущения!$H$59:$O$59,MATCH(H76,Допущения!$H$58:$O$58,1)),Допущения!$H$59)*IF(H2=0,1,Допущения!$E$19)) -> 30889 | I77: =IF(I76=0,0,I76*IFERROR(INDEX(Допущения!$H$59:$O$59,MATCH(I76,Допущения!$H$58:$O$58,1)),Допущения!$H$59)*IF(I2=0,1,Допущения!$E$19)) -> 37145 | J77: =IF(J76=0,0,J76*IFERROR(INDEX(Допущения!$H$59:$O$59,MATCH(J76,Допущения!$H$58:$O$58,1)),Допущения!$H$59)*IF(J2=0,1,Допущения!$E$19)) -> 42185 | ... AM77: =IF(AM76=0,0,AM76*IFERROR(INDEX(Допущения!$H$59:$O$59,MATCH(AM76,Допущения!$H$58:$O$58,1)),Допущения!$H$59)*IF(AM2=0,1,Допущения!$E$19)) -> 207192
A78: Colostrum: остаток на конец | C78: =C75-C21+C76 -> 1000 | D78: =D75-D21+D76 -> 1510.38 | E78: =E75-E21+E76 -> 2014.29 | F78: =F75-F21+F76 -> 2891.769 | G78: =G75-G21+G76 -> 3876.1721 | H78: =H75-H21+H76 -> 4850.5669 | I78: =I75-I21+I76 -> 5879.6369 | J78: =J75-J21+J76 -> 6894.6772 | ... AM78: =AM75-AM21+AM76 -> 37864.53
A79: Women's Probiotic: остаток на начало | C79: 0 | D79: =C82 -> 400 | E79: =D82 -> 599.718 | F79: =E82 -> 806.462 | G79: =F82 -> 1164.8776 | H79: =G82 -> 1552.6628 | I79: =H82 -> 1933.7968 | J79: =I82 -> 2315.1661 | K79: =J82 -> 2739.2889 | ... AM79: =AL82 -> 15081.022
A80: Women's Probiotic: перезаказ, банок | C80: =Допущения!$G$60 -> 400 | D80: =IF(Допущения!$B$41*E22>D79-D22,MAX(Допущения!$B$42,CEILING(Допущения!$B$41*E22-(D79-D22),50)),0) -> 350 | E80: =IF(Допущения!$B$41*F22>E79-E22,MAX(Допущения!$B$42,CEILING(Допущения!$B$41*F22-(E79-E22),50)),0) -> 650 | F80: =IF(Допущения!$B$41*G22>F79-F22,MAX(Допущения!$B$42,CEILING(Допущения!$B$41*G22-(F79-F22),50)),0) -> 950 | G80: =IF(Допущения!$B$41*H22>G79-G22,MAX(Допущения!$B$42,CEILING(Допущения!$B$41*H22-(G79-G22),50)),0) -> 1250 | H80: =IF(Допущения!$B$41*I22>H79-H22,MAX(Допущения!$B$42,CEILING(Допущения!$B$41*I22-(H79-H22),50)),0) -> 1550 | I80: =IF(Допущения!$B$41*J22>I79-I22,MAX(Допущения!$B$42,CEILING(Допущения!$B$41*J22-(I79-I22),50)),0) -> 1850 | J80: =IF(Допущения!$B$41*K22>J79-J22,MAX(Допущения!$B$42,CEILING(Допущения!$B$41*K22-(J79-J22),50)),0) -> 2200 | K80: =IF(Допущения!$B$41*L22>K79-K22,MAX(Допущения!$B$42,CEILING(Допущения!$B$41*L22-(K79-K22),50)),0) -> 2500 | ... AL80: =IF(Допущения!$B$41*AM22>AL79-AL22,MAX(Допущения!$B$42,CEILING(Допущения!$B$41*AM22-(AL79-AL22),50)),0) -> 11650 | AM80: =IF(Допущения!$B$41*AM22>AM79-AM22,MAX(Допущения!$B$42,CEILING(Допущения!$B$41*AM22-(AM79-AM22),50)),0) -> 11600
A81: Women's Probiotic: перезаказ, $ | C81: =IF(C80=0,0,C80*IFERROR(INDEX(Допущения!$H$60:$O$60,MATCH(C80,Допущения!$H$58:$O$58,1)),Допущения!$H$60)*IF(C2=0,1,Допущения!$E$19)) -> 3196 | D81: =IF(D80=0,0,D80*IFERROR(INDEX(Допущения!$H$60:$O$60,MATCH(D80,Допущения!$H$58:$O$58,1)),Допущения!$H$60)*IF(D2=0,1,Допущения!$E$19)) -> 2796.5 | E81: =IF(E80=0,0,E80*IFERROR(INDEX(Допущения!$H$60:$O$60,MATCH(E80,Допущения!$H$58:$O$58,1)),Допущения!$H$60)*IF(E2=0,1,Допущения!$E$19)) -> 4966 | F81: =IF(F80=0,0,F80*IFERROR(INDEX(Допущения!$H$60:$O$60,MATCH(F80,Допущения!$H$58:$O$58,1)),Допущения!$H$60)*IF(F2=0,1,Допущения!$E$19)) -> 7258 | G81: =IF(G80=0,0,G80*IFERROR(INDEX(Допущения!$H$60:$O$60,MATCH(G80,Допущения!$H$58:$O$58,1)),Допущения!$H$60)*IF(G2=0,1,Допущения!$E$19)) -> 9300 | H81: =IF(H80=0,0,H80*IFERROR(INDEX(Допущения!$H$60:$O$60,MATCH(H80,Допущения!$H$58:$O$58,1)),Допущения!$H$60)*IF(H2=0,1,Допущения!$E$19)) -> 11532 | I81: =IF(I80=0,0,I80*IFERROR(INDEX(Допущения!$H$60:$O$60,MATCH(I80,Допущения!$H$58:$O$58,1)),Допущения!$H$60)*IF(I2=0,1,Допущения!$E$19)) -> 13764 | J81: =IF(J80=0,0,J80*IFERROR(INDEX(Допущения!$H$60:$O$60,MATCH(J80,Допущения!$H$58:$O$58,1)),Допущения!$H$60)*IF(J2=0,1,Допущения!$E$19)) -> 16368 | ... AM81: =IF(AM80=0,0,AM80*IFERROR(INDEX(Допущения!$H$60:$O$60,MATCH(AM80,Допущения!$H$58:$O$58,1)),Допущения!$H$60)*IF(AM2=0,1,Допущения!$E$19)) -> 76444
A82: Women's Probiotic: остаток на конец | C82: =C79-C22+C80 -> 400 | D82: =D79-D22+D80 -> 599.718 | E82: =E79-E22+E80 -> 806.462 | F82: =F79-F22+F80 -> 1164.8776 | G82: =G79-G22+G80 -> 1552.6628 | H82: =H79-H22+H80 -> 1933.7968 | I82: =I79-I22+I80 -> 2315.1661 | J82: =J79-J22+J80 -> 2739.2889 | ... AM82: =AM79-AM22+AM80 -> 15100.704
A83: Magnesium Glycinate: остаток на начало | C83: 0 | D83: =C86 -> 1000 | E83: =D86 -> 1071.7 | F83: =E86 -> 1450.0825 | G83: =F86 -> 2101.7517 | H83: =G86 -> 2850.1141 | I83: =H86 -> 3544.6502 | J83: =I86 -> 4245.106 | K83: =J86 -> 4987.4529 | ... AM83: =AL86 -> 27808.024
A84: Magnesium Glycinate: перезаказ, банок | C84: =Допущения!$G$61 -> 1000 | D84: =IF(Допущения!$B$41*E23>D83-D23,MAX(Допущения!$B$42,CEILING(Допущения!$B$41*E23-(D83-D23),50)),0) -> 350 | E84: =IF(Допущения!$B$41*F23>E83-E23,MAX(Допущения!$B$42,CEILING(Допущения!$B$41*F23-(E83-E23),50)),0) -> 1200 | F84: =IF(Допущения!$B$41*G23>F83-F23,MAX(Допущения!$B$42,CEILING(Допущения!$B$41*G23-(F83-F23),50)),0) -> 1750 | G84: =IF(Допущения!$B$41*H23>G83-G23,MAX(Допущения!$B$42,CEILING(Допущения!$B$41*H23-(G83-G23),50)),0) -> 2350 | H84: =IF(Допущения!$B$41*I23>H83-H23,MAX(Допущения!$B$42,CEILING(Допущения!$B$41*I23-(H83-H23),50)),0) -> 2850 | I84: =IF(Допущения!$B$41*J23>I83-I23,MAX(Допущения!$B$42,CEILING(Допущения!$B$41*J23-(I83-I23),50)),0) -> 3400 | J84: =IF(Допущения!$B$41*K23>J83-J23,MAX(Допущения!$B$42,CEILING(Допущения!$B$41*K23-(J83-J23),50)),0) -> 4000 | K84: =IF(Допущения!$B$41*L23>K83-K23,MAX(Допущения!$B$42,CEILING(Допущения!$B$41*L23-(K83-K23),50)),0) -> 4600 | ... AL84: =IF(Допущения!$B$41*AM23>AL83-AL23,MAX(Допущения!$B$42,CEILING(Допущения!$B$41*AM23-(AL83-AL23),50)),0) -> 21500 | AM84: =IF(Допущения!$B$41*AM23>AM83-AM23,MAX(Допущения!$B$42,CEILING(Допущения!$B$41*AM23-(AM83-AM23),50)),0) -> 21350
A85: Magnesium Glycinate: перезаказ, $ | C85: =IF(C84=0,0,C84*IFERROR(INDEX(Допущения!$H$61:$O$61,MATCH(C84,Допущения!$H$58:$O$58,1)),Допущения!$H$61)*IF(C2=0,1,Допущения!$E$19)) -> 4610 | D85: =IF(D84=0,0,D84*IFERROR(INDEX(Допущения!$H$61:$O$61,MATCH(D84,Допущения!$H$58:$O$58,1)),Допущения!$H$61)*IF(D2=0,1,Допущения!$E$19)) -> 1806 | E85: =IF(E84=0,0,E84*IFERROR(INDEX(Допущения!$H$61:$O$61,MATCH(E84,Допущения!$H$58:$O$58,1)),Допущения!$H$61)*IF(E2=0,1,Допущения!$E$19)) -> 5532 | F85: =IF(F84=0,0,F84*IFERROR(INDEX(Допущения!$H$61:$O$61,MATCH(F84,Допущения!$H$58:$O$58,1)),Допущения!$H$61)*IF(F2=0,1,Допущения!$E$19)) -> 8067.5 | G85: =IF(G84=0,0,G84*IFERROR(INDEX(Допущения!$H$61:$O$61,MATCH(G84,Допущения!$H$58:$O$58,1)),Допущения!$H$61)*IF(G2=0,1,Допущения!$E$19)) -> 10833.5 | H85: =IF(H84=0,0,H84*IFERROR(INDEX(Допущения!$H$61:$O$61,MATCH(H84,Допущения!$H$58:$O$58,1)),Допущения!$H$61)*IF(H2=0,1,Допущения!$E$19)) -> 12568.5 | I85: =IF(I84=0,0,I84*IFERROR(INDEX(Допущения!$H$61:$O$61,MATCH(I84,Допущения!$H$58:$O$58,1)),Допущения!$H$61)*IF(I2=0,1,Допущения!$E$19)) -> 14994 | J85: =IF(J84=0,0,J84*IFERROR(INDEX(Допущения!$H$61:$O$61,MATCH(J84,Допущения!$H$58:$O$58,1)),Допущения!$H$61)*IF(J2=0,1,Допущения!$E$19)) -> 17640 | ... AM85: =IF(AM84=0,0,AM84*IFERROR(INDEX(Допущения!$H$61:$O$61,MATCH(AM84,Допущения!$H$58:$O$58,1)),Допущения!$H$61)*IF(AM2=0,1,Допущения!$E$19)) -> 80276
A86: Magnesium Glycinate: остаток на конец | C86: =C83-C23+C84 -> 1000 | D86: =D83-D23+D84 -> 1071.7 | E86: =E83-E23+E84 -> 1450.0825 | F86: =F83-F23+F84 -> 2101.7517 | G86: =G83-G23+G84 -> 2850.1141 | H86: =H83-H23+H84 -> 3544.6502 | I86: =I83-I23+I84 -> 4245.106 | J86: =J83-J23+J84 -> 4987.4529 | ... AM86: =AM83-AM23+AM84 -> 27787.227
A87: Creatine: остаток на начало | C87: 0 | D87: =C90 -> 200 | E87: =D90 -> 277.642 | F87: =E90 -> 324.04025 | G87: =F90 -> 474.81518 | H87: =G90 -> 772.45941 | I87: =H90 -> 1000.465 | J87: =I90 -> 1282.6066 | K87: =J90 -> 1517.4813 | ... AM87: =AL90 -> 6642.027
A88: Creatine: перезаказ, банок | C88: =Допущения!$G$62 -> 200 | D88: =IF(Допущения!$B$41*E24>D87-D24,MAX(Допущения!$B$42,CEILING(Допущения!$B$41*E24-(D87-D24),50)),0) -> 150 | E88: =IF(Допущения!$B$41*F24>E87-E24,MAX(Допущения!$B$42,CEILING(Допущения!$B$41*F24-(E87-E24),50)),0) -> 250 | F88: =IF(Допущения!$B$41*G24>F87-F24,MAX(Допущения!$B$42,CEILING(Допущения!$B$41*G24-(F87-F24),50)),0) -> 400 | G88: =IF(Допущения!$B$41*H24>G87-G24,MAX(Допущения!$B$42,CEILING(Допущения!$B$41*H24-(G87-G24),50)),0) -> 650 | H88: =IF(Допущения!$B$41*I24>H87-H24,MAX(Допущения!$B$42,CEILING(Допущения!$B$41*I24-(H87-H24),50)),0) -> 800 | I88: =IF(Допущения!$B$41*J24>I87-I24,MAX(Допущения!$B$42,CEILING(Допущения!$B$41*J24-(I87-I24),50)),0) -> 1050 | J88: =IF(Допущения!$B$41*K24>J87-J24,MAX(Допущения!$B$42,CEILING(Допущения!$B$41*K24-(J87-J24),50)),0) -> 1200 | K88: =IF(Допущения!$B$41*L24>K87-K24,MAX(Допущения!$B$42,CEILING(Допущения!$B$41*L24-(K87-K24),50)),0) -> 1450 | ... AL88: =IF(Допущения!$B$41*AM24>AL87-AL24,MAX(Допущения!$B$42,CEILING(Допущения!$B$41*AM24-(AL87-AL24),50)),0) -> 5100 | AM88: =IF(Допущения!$B$41*AM24>AM87-AM24,MAX(Допущения!$B$42,CEILING(Допущения!$B$41*AM24-(AM87-AM24),50)),0) -> 5050
A89: Creatine: перезаказ, $ | C89: =IF(C88=0,0,C88*IFERROR(INDEX(Допущения!$H$62:$O$62,MATCH(C88,Допущения!$H$58:$O$58,1)),Допущения!$H$62)*IF(C2=0,1,Допущения!$E$19)) -> 1380 | D89: =IF(D88=0,0,D88*IFERROR(INDEX(Допущения!$H$62:$O$62,MATCH(D88,Допущения!$H$58:$O$58,1)),Допущения!$H$62)*IF(D2=0,1,Допущения!$E$19)) -> 1035 | E89: =IF(E88=0,0,E88*IFERROR(INDEX(Допущения!$H$62:$O$62,MATCH(E88,Допущения!$H$58:$O$58,1)),Допущения!$H$62)*IF(E2=0,1,Допущения!$E$19)) -> 1725 | F89: =IF(F88=0,0,F88*IFERROR(INDEX(Допущения!$H$62:$O$62,MATCH(F88,Допущения!$H$58:$O$58,1)),Допущения!$H$62)*IF(F2=0,1,Допущения!$E$19)) -> 2700 | G89: =IF(G88=0,0,G88*IFERROR(INDEX(Допущения!$H$62:$O$62,MATCH(G88,Допущения!$H$58:$O$58,1)),Допущения!$H$62)*IF(G2=0,1,Допущения!$E$19)) -> 4225 | H89: =IF(H88=0,0,H88*IFERROR(INDEX(Допущения!$H$62:$O$62,MATCH(H88,Допущения!$H$58:$O$58,1)),Допущения!$H$62)*IF(H2=0,1,Допущения!$E$19)) -> 5200 | I89: =IF(I88=0,0,I88*IFERROR(INDEX(Допущения!$H$62:$O$62,MATCH(I88,Допущения!$H$58:$O$58,1)),Допущения!$H$62)*IF(I2=0,1,Допущения!$E$19)) -> 6667.5 | J89: =IF(J88=0,0,J88*IFERROR(INDEX(Допущения!$H$62:$O$62,MATCH(J88,Допущения!$H$58:$O$58,1)),Допущения!$H$62)*IF(J2=0,1,Допущения!$E$19)) -> 7620 | ... AM89: =IF(AM88=0,0,AM88*IFERROR(INDEX(Допущения!$H$62:$O$62,MATCH(AM88,Допущения!$H$58:$O$58,1)),Допущения!$H$62)*IF(AM2=0,1,Допущения!$E$19)) -> 30552.5
A90: Creatine: остаток на конец | C90: =C87-C24+C88 -> 200 | D90: =D87-D24+D88 -> 277.642 | E90: =E87-E24+E88 -> 324.04025 | F90: =F87-F24+F88 -> 474.81518 | G90: =G87-G24+G88 -> 772.45941 | H90: =H87-H24+H88 -> 1000.465 | I90: =I87-I24+I88 -> 1282.6066 | J90: =J87-J24+J88 -> 1517.4813 | ... AM90: =AM87-AM24+AM88 -> 6609.9074
